
{
    "Connected": true,
    "Room": "https://appr.tc/r/96598265201105947",
    "StatsArray": [
        {
            "candidate-pair": {
                "b18b89bb": {
                    "id": "b18b89bb",
                    "timestamp": "1624451176436",
                    "localCandidateId": "59ba6e0b",
                    "remoteCandidateId": "d9b257e6",
                    "state": "succeeded",
                    "priority": "9115005270282359000",
                    "nominated": "true",
                    "bytesSent": "508838",
                    "currentRoundTripTime": "NA",
                    "totalRoundTripTime": "NA",
                    "bytesReceived": "485866"
                },
                "bb8c1d68": {
                    "id": "bb8c1d68",
                    "timestamp": "1624451176436",
                    "localCandidateId": "1698ae52",
                    "remoteCandidateId": "dfbb0ae2",
                    "state": "succeeded",
                    "priority": "9114723795305512000",
                    "nominated": "true",
                    "bytesSent": "11612",
                    "currentRoundTripTime": "NA",
                    "totalRoundTripTime": "NA",
                    "bytesReceived": "7180"
                },
                "653ab543": {
                    "id": "653ab543",
                    "timestamp": "1624451176436",
                    "localCandidateId": "1698ae52",
                    "remoteCandidateId": "dcaacc16",
                    "state": "inprogress",
                    "priority": "7241259335668204000",
                    "nominated": "false",
                    "bytesSent": "0",
                    "currentRoundTripTime": "NA",
                    "totalRoundTripTime": "NA",
                    "bytesReceived": "0"
                }
            },
            "inbound-rtp": {
                "3e8e63a7": {
                    "id": "3e8e63a7",
                    "timestamp": "1624451176436",
                    "ssrc": "520498122",
                    "kind": "audio",
                    "transportId": "NA",
                    "codecId": "NA",
                    "packetsReceived": "120",
                    "packetsLost": "0",
                    "packetsDiscarded": "NA",
                    "jitter": "0",
                    "bytesReceived": "21732",
                    "receiverId": "NA",
                    "remoteId": "70d43d81",
                    "nackCount": "0",
                    "audioLevel": "NA",
                    "framesDecoded": "NA",
                    "framesReceived": "NA",
                    "framesDropped": "NA",
                    "partialFramesLost": "NA",
                    "totalAudioEnergy": "NA",
                    "totalSamplesDuration": "NA"
                },
                "d13ac7e8": {
                    "id": "d13ac7e8",
                    "timestamp": "1624451176436",
                    "ssrc": "4223424412",
                    "kind": "video",
                    "transportId": "NA",
                    "codecId": "NA",
                    "packetsReceived": "438",
                    "packetsLost": "0",
                    "packetsDiscarded": "NA",
                    "jitter": "0.007",
                    "bytesReceived": "460817",
                    "receiverId": "NA",
                    "remoteId": "e0bb0faa",
                    "nackCount": "0",
                    "audioLevel": "NA",
                    "framesDecoded": "52",
                    "framesReceived": "NA",
                    "framesDropped": "NA",
                    "partialFramesLost": "NA",
                    "totalAudioEnergy": "NA",
                    "totalSamplesDuration": "NA"
                }
            },
            "local-candidate": {
                "1698ae52": {
                    "id": "1698ae52",
                    "timestamp": "1624451176436",
                    "address": "192.168.1.12",
                    "port": "57389",
                    "protocol": "udp",
                    "candidateType": "host",
                    "url": "NA"
                },
                "718e1a6f": {
                    "id": "718e1a6f",
                    "timestamp": "1624451176436",
                    "address": "2.87.64.185",
                    "port": "57389",
                    "protocol": "udp",
                    "candidateType": "srflx",
                    "url": "NA"
                },
                "59ba6e0b": {
                    "id": "59ba6e0b",
                    "timestamp": "1624451176436",
                    "address": "2a02:587:3e07:5100:e950:d005:6847:63d8",
                    "port": "57390",
                    "protocol": "udp",
                    "candidateType": "host",
                    "url": "NA"
                },
                "eb49fe10": {
                    "id": "eb49fe10",
                    "timestamp": "1624451176436",
                    "address": "192.168.1.12",
                    "port": "55528",
                    "protocol": "tcp",
                    "candidateType": "host",
                    "url": "NA"
                },
                "e0281fa6": {
                    "id": "e0281fa6",
                    "timestamp": "1624451176436",
                    "address": "2a02:587:3e07:5100:e950:d005:6847:63d8",
                    "port": "59550",
                    "protocol": "tcp",
                    "candidateType": "host",
                    "url": "NA"
                }
            },
            "outbound-rtp": {
                "436e0425": {
                    "id": "436e0425",
                    "timestamp": "1624451176436",
                    "ssrc": "3432877157",
                    "kind": "audio",
                    "transportId": "NA",
                    "codecId": "NA",
                    "packetsSent": "120",
                    "bytesSent": "12120",
                    "senderId": "NA",
                    "remoteId": "NA",
                    "nackCount": "0",
                    "framesEncoded": "NA",
                    "framesSent": "NA",
                    "framesPerSecond": "NA"
                },
                "8f34652c": {
                    "id": "8f34652c",
                    "timestamp": "1624451176436",
                    "ssrc": "3414702279",
                    "kind": "video",
                    "transportId": "NA",
                    "codecId": "NA",
                    "packetsSent": "455",
                    "bytesSent": "498603",
                    "senderId": "NA",
                    "remoteId": "c61fe2f2",
                    "nackCount": "0",
                    "framesEncoded": "55",
                    "framesSent": "NA",
                    "framesPerSecond": "NA"
                }
            },
            "remote-candidate": {
                "dfbb0ae2": {
                    "id": "dfbb0ae2",
                    "timestamp": "1624451176436",
                    "address": "192.168.1.12",
                    "port": "53417",
                    "protocol": "udp",
                    "candidateType": "host",
                    "url": "NA"
                },
                "d9b257e6": {
                    "id": "d9b257e6",
                    "timestamp": "1624451176436",
                    "address": "2a02:587:3e07:5100:e950:d005:6847:63d8",
                    "port": "57532",
                    "protocol": "udp",
                    "candidateType": "host",
                    "url": "NA"
                },
                "dcaacc16": {
                    "id": "dcaacc16",
                    "timestamp": "1624451176436",
                    "address": "2.87.64.185",
                    "port": "53417",
                    "protocol": "udp",
                    "candidateType": "srflx",
                    "url": "NA"
                }
            }
        },
        {
            "candidate-pair": {
                "b18b89bb": {
                    "id": "b18b89bb",
                    "timestamp": "1624451178503",
                    "localCandidateId": "59ba6e0b",
                    "remoteCandidateId": "d9b257e6",
                    "state": "succeeded",
                    "priority": "9115005270282359000",
                    "nominated": "true",
                    "bytesSent": "1058441",
                    "currentRoundTripTime": "NA",
                    "totalRoundTripTime": "NA",
                    "bytesReceived": "909481"
                },
                "bb8c1d68": {
                    "id": "bb8c1d68",
                    "timestamp": "1624451178503",
                    "localCandidateId": "1698ae52",
                    "remoteCandidateId": "dfbb0ae2",
                    "state": "succeeded",
                    "priority": "9114723795305512000",
                    "nominated": "true",
                    "bytesSent": "11612",
                    "currentRoundTripTime": "NA",
                    "totalRoundTripTime": "NA",
                    "bytesReceived": "7180"
                },
                "653ab543": {
                    "id": "653ab543",
                    "timestamp": "1624451178503",
                    "localCandidateId": "1698ae52",
                    "remoteCandidateId": "dcaacc16",
                    "state": "inprogress",
                    "priority": "7241259335668204000",
                    "nominated": "false",
                    "bytesSent": "0",
                    "currentRoundTripTime": "NA",
                    "totalRoundTripTime": "NA",
                    "bytesReceived": "0"
                }
            },
            "inbound-rtp": {
                "3e8e63a7": {
                    "id": "3e8e63a7",
                    "timestamp": "1624451178504",
                    "ssrc": "520498122",
                    "kind": "audio",
                    "transportId": "NA",
                    "codecId": "NA",
                    "packetsReceived": "223",
                    "packetsLost": "0",
                    "packetsDiscarded": "NA",
                    "jitter": "0",
                    "bytesReceived": "40363",
                    "receiverId": "NA",
                    "remoteId": "70d43d81",
                    "nackCount": "0",
                    "audioLevel": "NA",
                    "framesDecoded": "NA",
                    "framesReceived": "NA",
                    "framesDropped": "NA",
                    "partialFramesLost": "NA",
                    "totalAudioEnergy": "NA",
                    "totalSamplesDuration": "NA"
                },
                "d13ac7e8": {
                    "id": "d13ac7e8",
                    "timestamp": "1624451178504",
                    "ssrc": "4223424412",
                    "kind": "video",
                    "transportId": "NA",
                    "codecId": "NA",
                    "packetsReceived": "801",
                    "packetsLost": "0",
                    "packetsDiscarded": "NA",
                    "jitter": "0.009",
                    "bytesReceived": "858457",
                    "receiverId": "NA",
                    "remoteId": "e0bb0faa",
                    "nackCount": "0",
                    "audioLevel": "NA",
                    "framesDecoded": "112",
                    "framesReceived": "NA",
                    "framesDropped": "NA",
                    "partialFramesLost": "NA",
                    "totalAudioEnergy": "NA",
                    "totalSamplesDuration": "NA"
                }
            },
            "local-candidate": {
                "1698ae52": {
                    "id": "1698ae52",
                    "timestamp": "1624451178503",
                    "address": "192.168.1.12",
                    "port": "57389",
                    "protocol": "udp",
                    "candidateType": "host",
                    "url": "NA"
                },
                "718e1a6f": {
                    "id": "718e1a6f",
                    "timestamp": "1624451178503",
                    "address": "2.87.64.185",
                    "port": "57389",
                    "protocol": "udp",
                    "candidateType": "srflx",
                    "url": "NA"
                },
                "59ba6e0b": {
                    "id": "59ba6e0b",
                    "timestamp": "1624451178503",
                    "address": "2a02:587:3e07:5100:e950:d005:6847:63d8",
                    "port": "57390",
                    "protocol": "udp",
                    "candidateType": "host",
                    "url": "NA"
                },
                "eb49fe10": {
                    "id": "eb49fe10",
                    "timestamp": "1624451178503",
                    "address": "192.168.1.12",
                    "port": "55528",
                    "protocol": "tcp",
                    "candidateType": "host",
                    "url": "NA"
                },
                "e0281fa6": {
                    "id": "e0281fa6",
                    "timestamp": "1624451178503",
                    "address": "2a02:587:3e07:5100:e950:d005:6847:63d8",
                    "port": "59550",
                    "protocol": "tcp",
                    "candidateType": "host",
                    "url": "NA"
                }
            },
            "outbound-rtp": {
                "436e0425": {
                    "id": "436e0425",
                    "timestamp": "1624451178503",
                    "ssrc": "3432877157",
                    "kind": "audio",
                    "transportId": "NA",
                    "codecId": "NA",
                    "packetsSent": "222",
                    "bytesSent": "22422",
                    "senderId": "NA",
                    "remoteId": "NA",
                    "nackCount": "0",
                    "framesEncoded": "NA",
                    "framesSent": "NA",
                    "framesPerSecond": "NA"
                },
                "8f34652c": {
                    "id": "8f34652c",
                    "timestamp": "1624451178503",
                    "ssrc": "3414702279",
                    "kind": "video",
                    "transportId": "NA",
                    "codecId": "NA",
                    "packetsSent": "932",
                    "bytesSent": "1029074",
                    "senderId": "NA",
                    "remoteId": "c61fe2f2",
                    "nackCount": "0",
                    "framesEncoded": "114",
                    "framesSent": "NA",
                    "framesPerSecond": "NA"
                }
            },
            "remote-candidate": {
                "dfbb0ae2": {
                    "id": "dfbb0ae2",
                    "timestamp": "1624451178503",
                    "address": "192.168.1.12",
                    "port": "53417",
                    "protocol": "udp",
                    "candidateType": "host",
                    "url": "NA"
                },
                "d9b257e6": {
                    "id": "d9b257e6",
                    "timestamp": "1624451178503",
                    "address": "2a02:587:3e07:5100:e950:d005:6847:63d8",
                    "port": "57532",
                    "protocol": "udp",
                    "candidateType": "host",
                    "url": "NA"
                },
                "dcaacc16": {
                    "id": "dcaacc16",
                    "timestamp": "1624451178503",
                    "address": "2.87.64.185",
                    "port": "53417",
                    "protocol": "udp",
                    "candidateType": "srflx",
                    "url": "NA"
                }
            }
        },
        {
            "candidate-pair": {
                "b18b89bb": {
                    "id": "b18b89bb",
                    "timestamp": "1624451180578",
                    "localCandidateId": "59ba6e0b",
                    "remoteCandidateId": "d9b257e6",
                    "state": "succeeded",
                    "priority": "9115005270282359000",
                    "nominated": "true",
                    "bytesSent": "1525595",
                    "currentRoundTripTime": "NA",
                    "totalRoundTripTime": "NA",
                    "bytesReceived": "1384369"
                },
                "bb8c1d68": {
                    "id": "bb8c1d68",
                    "timestamp": "1624451180578",
                    "localCandidateId": "1698ae52",
                    "remoteCandidateId": "dfbb0ae2",
                    "state": "succeeded",
                    "priority": "9114723795305512000",
                    "nominated": "true",
                    "bytesSent": "11612",
                    "currentRoundTripTime": "NA",
                    "totalRoundTripTime": "NA",
                    "bytesReceived": "7180"
                },
                "653ab543": {
                    "id": "653ab543",
                    "timestamp": "1624451180578",
                    "localCandidateId": "1698ae52",
                    "remoteCandidateId": "dcaacc16",
                    "state": "inprogress",
                    "priority": "7241259335668204000",
                    "nominated": "false",
                    "bytesSent": "0",
                    "currentRoundTripTime": "NA",
                    "totalRoundTripTime": "NA",
                    "bytesReceived": "0"
                }
            },
            "inbound-rtp": {
                "3e8e63a7": {
                    "id": "3e8e63a7",
                    "timestamp": "1624451180578",
                    "ssrc": "520498122",
                    "kind": "audio",
                    "transportId": "NA",
                    "codecId": "NA",
                    "packetsReceived": "328",
                    "packetsLost": "0",
                    "packetsDiscarded": "NA",
                    "jitter": "0.003",
                    "bytesReceived": "58264",
                    "receiverId": "NA",
                    "remoteId": "70d43d81",
                    "nackCount": "0",
                    "audioLevel": "NA",
                    "framesDecoded": "NA",
                    "framesReceived": "NA",
                    "framesDropped": "NA",
                    "partialFramesLost": "NA",
                    "totalAudioEnergy": "NA",
                    "totalSamplesDuration": "NA"
                },
                "d13ac7e8": {
                    "id": "d13ac7e8",
                    "timestamp": "1624451180578",
                    "ssrc": "4223424412",
                    "kind": "video",
                    "transportId": "NA",
                    "codecId": "NA",
                    "packetsReceived": "1198",
                    "packetsLost": "0",
                    "packetsDiscarded": "NA",
                    "jitter": "0.019",
                    "bytesReceived": "1308072",
                    "receiverId": "NA",
                    "remoteId": "e0bb0faa",
                    "nackCount": "0",
                    "audioLevel": "NA",
                    "framesDecoded": "162",
                    "framesReceived": "NA",
                    "framesDropped": "NA",
                    "partialFramesLost": "NA",
                    "totalAudioEnergy": "NA",
                    "totalSamplesDuration": "NA"
                }
            },
            "local-candidate": {
                "1698ae52": {
                    "id": "1698ae52",
                    "timestamp": "1624451180578",
                    "address": "192.168.1.12",
                    "port": "57389",
                    "protocol": "udp",
                    "candidateType": "host",
                    "url": "NA"
                },
                "718e1a6f": {
                    "id": "718e1a6f",
                    "timestamp": "1624451180578",
                    "address": "2.87.64.185",
                    "port": "57389",
                    "protocol": "udp",
                    "candidateType": "srflx",
                    "url": "NA"
                },
                "59ba6e0b": {
                    "id": "59ba6e0b",
                    "timestamp": "1624451180578",
                    "address": "2a02:587:3e07:5100:e950:d005:6847:63d8",
                    "port": "57390",
                    "protocol": "udp",
                    "candidateType": "host",
                    "url": "NA"
                },
                "eb49fe10": {
                    "id": "eb49fe10",
                    "timestamp": "1624451180578",
                    "address": "192.168.1.12",
                    "port": "55528",
                    "protocol": "tcp",
                    "candidateType": "host",
                    "url": "NA"
                },
                "e0281fa6": {
                    "id": "e0281fa6",
                    "timestamp": "1624451180578",
                    "address": "2a02:587:3e07:5100:e950:d005:6847:63d8",
                    "port": "59550",
                    "protocol": "tcp",
                    "candidateType": "host",
                    "url": "NA"
                }
            },
            "outbound-rtp": {
                "436e0425": {
                    "id": "436e0425",
                    "timestamp": "1624451180578",
                    "ssrc": "3432877157",
                    "kind": "audio",
                    "transportId": "NA",
                    "codecId": "NA",
                    "packetsSent": "327",
                    "bytesSent": "31236",
                    "senderId": "NA",
                    "remoteId": "NA",
                    "nackCount": "0",
                    "framesEncoded": "NA",
                    "framesSent": "NA",
                    "framesPerSecond": "NA"
                },
                "8f34652c": {
                    "id": "8f34652c",
                    "timestamp": "1624451180578",
                    "ssrc": "3414702279",
                    "kind": "video",
                    "transportId": "NA",
                    "codecId": "NA",
                    "packetsSent": "1335",
                    "bytesSent": "1479706",
                    "senderId": "NA",
                    "remoteId": "c61fe2f2",
                    "nackCount": "0",
                    "framesEncoded": "167",
                    "framesSent": "NA",
                    "framesPerSecond": "NA"
                }
            },
            "remote-candidate": {
                "dfbb0ae2": {
                    "id": "dfbb0ae2",
                    "timestamp": "1624451180578",
                    "address": "192.168.1.12",
                    "port": "53417",
                    "protocol": "udp",
                    "candidateType": "host",
                    "url": "NA"
                },
                "d9b257e6": {
                    "id": "d9b257e6",
                    "timestamp": "1624451180578",
                    "address": "2a02:587:3e07:5100:e950:d005:6847:63d8",
                    "port": "57532",
                    "protocol": "udp",
                    "candidateType": "host",
                    "url": "NA"
                },
                "dcaacc16": {
                    "id": "dcaacc16",
                    "timestamp": "1624451180578",
                    "address": "2.87.64.185",
                    "port": "53417",
                    "protocol": "udp",
                    "candidateType": "srflx",
                    "url": "NA"
                }
            }
        },
        {
            "candidate-pair": {
                "b18b89bb": {
                    "id": "b18b89bb",
                    "timestamp": "1624451182628",
                    "localCandidateId": "59ba6e0b",
                    "remoteCandidateId": "d9b257e6",
                    "state": "succeeded",
                    "priority": "9115005270282359000",
                    "nominated": "true",
                    "bytesSent": "2118131",
                    "currentRoundTripTime": "NA",
                    "totalRoundTripTime": "NA",
                    "bytesReceived": "2141427"
                },
                "bb8c1d68": {
                    "id": "bb8c1d68",
                    "timestamp": "1624451182628",
                    "localCandidateId": "1698ae52",
                    "remoteCandidateId": "dfbb0ae2",
                    "state": "succeeded",
                    "priority": "9114723795305512000",
                    "nominated": "true",
                    "bytesSent": "11612",
                    "currentRoundTripTime": "NA",
                    "totalRoundTripTime": "NA",
                    "bytesReceived": "7180"
                },
                "653ab543": {
                    "id": "653ab543",
                    "timestamp": "1624451182628",
                    "localCandidateId": "1698ae52",
                    "remoteCandidateId": "dcaacc16",
                    "state": "inprogress",
                    "priority": "7241259335668204000",
                    "nominated": "false",
                    "bytesSent": "0",
                    "currentRoundTripTime": "NA",
                    "totalRoundTripTime": "NA",
                    "bytesReceived": "0"
                }
            },
            "inbound-rtp": {
                "3e8e63a7": {
                    "id": "3e8e63a7",
                    "timestamp": "1624451182628",
                    "ssrc": "520498122",
                    "kind": "audio",
                    "transportId": "NA",
                    "codecId": "NA",
                    "packetsReceived": "430",
                    "packetsLost": "0",
                    "packetsDiscarded": "NA",
                    "jitter": "0.003",
                    "bytesReceived": "76699",
                    "receiverId": "NA",
                    "remoteId": "70d43d81",
                    "nackCount": "0",
                    "audioLevel": "NA",
                    "framesDecoded": "NA",
                    "framesReceived": "NA",
                    "framesDropped": "NA",
                    "partialFramesLost": "NA",
                    "totalAudioEnergy": "NA",
                    "totalSamplesDuration": "NA"
                },
                "d13ac7e8": {
                    "id": "d13ac7e8",
                    "timestamp": "1624451182628",
                    "ssrc": "4223424412",
                    "kind": "video",
                    "transportId": "NA",
                    "codecId": "NA",
                    "packetsReceived": "1839",
                    "packetsLost": "0",
                    "packetsDiscarded": "NA",
                    "jitter": "0.019",
                    "bytesReceived": "2036083",
                    "receiverId": "NA",
                    "remoteId": "e0bb0faa",
                    "nackCount": "0",
                    "audioLevel": "NA",
                    "framesDecoded": "215",
                    "framesReceived": "NA",
                    "framesDropped": "NA",
                    "partialFramesLost": "NA",
                    "totalAudioEnergy": "NA",
                    "totalSamplesDuration": "NA"
                }
            },
            "local-candidate": {
                "1698ae52": {
                    "id": "1698ae52",
                    "timestamp": "1624451182628",
                    "address": "192.168.1.12",
                    "port": "57389",
                    "protocol": "udp",
                    "candidateType": "host",
                    "url": "NA"
                },
                "718e1a6f": {
                    "id": "718e1a6f",
                    "timestamp": "1624451182628",
                    "address": "2.87.64.185",
                    "port": "57389",
                    "protocol": "udp",
                    "candidateType": "srflx",
                    "url": "NA"
                },
                "59ba6e0b": {
                    "id": "59ba6e0b",
                    "timestamp": "1624451182628",
                    "address": "2a02:587:3e07:5100:e950:d005:6847:63d8",
                    "port": "57390",
                    "protocol": "udp",
                    "candidateType": "host",
                    "url": "NA"
                },
                "eb49fe10": {
                    "id": "eb49fe10",
                    "timestamp": "1624451182628",
                    "address": "192.168.1.12",
                    "port": "55528",
                    "protocol": "tcp",
                    "candidateType": "host",
                    "url": "NA"
                },
                "e0281fa6": {
                    "id": "e0281fa6",
                    "timestamp": "1624451182628",
                    "address": "2a02:587:3e07:5100:e950:d005:6847:63d8",
                    "port": "59550",
                    "protocol": "tcp",
                    "candidateType": "host",
                    "url": "NA"
                }
            },
            "outbound-rtp": {
                "436e0425": {
                    "id": "436e0425",
                    "timestamp": "1624451182628",
                    "ssrc": "3432877157",
                    "kind": "audio",
                    "transportId": "NA",
                    "codecId": "NA",
                    "packetsSent": "430",
                    "bytesSent": "37909",
                    "senderId": "NA",
                    "remoteId": "ed977358",
                    "nackCount": "0",
                    "framesEncoded": "NA",
                    "framesSent": "NA",
                    "framesPerSecond": "NA"
                },
                "8f34652c": {
                    "id": "8f34652c",
                    "timestamp": "1624451182628",
                    "ssrc": "3414702279",
                    "kind": "video",
                    "transportId": "NA",
                    "codecId": "NA",
                    "packetsSent": "1849",
                    "bytesSent": "2056057",
                    "senderId": "NA",
                    "remoteId": "c61fe2f2",
                    "nackCount": "0",
                    "framesEncoded": "226",
                    "framesSent": "NA",
                    "framesPerSecond": "NA"
                }
            },
            "remote-candidate": {
                "dfbb0ae2": {
                    "id": "dfbb0ae2",
                    "timestamp": "1624451182628",
                    "address": "192.168.1.12",
                    "port": "53417",
                    "protocol": "udp",
                    "candidateType": "host",
                    "url": "NA"
                },
                "d9b257e6": {
                    "id": "d9b257e6",
                    "timestamp": "1624451182628",
                    "address": "2a02:587:3e07:5100:e950:d005:6847:63d8",
                    "port": "57532",
                    "protocol": "udp",
                    "candidateType": "host",
                    "url": "NA"
                },
                "dcaacc16": {
                    "id": "dcaacc16",
                    "timestamp": "1624451182628",
                    "address": "2.87.64.185",
                    "port": "53417",
                    "protocol": "udp",
                    "candidateType": "srflx",
                    "url": "NA"
                }
            }
        },
        {
            "candidate-pair": {
                "b18b89bb": {
                    "id": "b18b89bb",
                    "timestamp": "1624451184671",
                    "localCandidateId": "59ba6e0b",
                    "remoteCandidateId": "d9b257e6",
                    "state": "succeeded",
                    "priority": "9115005270282359000",
                    "nominated": "true",
                    "bytesSent": "2581337",
                    "currentRoundTripTime": "NA",
                    "totalRoundTripTime": "NA",
                    "bytesReceived": "2798759"
                },
                "bb8c1d68": {
                    "id": "bb8c1d68",
                    "timestamp": "1624451184671",
                    "localCandidateId": "1698ae52",
                    "remoteCandidateId": "dfbb0ae2",
                    "state": "succeeded",
                    "priority": "9114723795305512000",
                    "nominated": "true",
                    "bytesSent": "11612",
                    "currentRoundTripTime": "NA",
                    "totalRoundTripTime": "NA",
                    "bytesReceived": "7180"
                },
                "653ab543": {
                    "id": "653ab543",
                    "timestamp": "1624451184671",
                    "localCandidateId": "1698ae52",
                    "remoteCandidateId": "dcaacc16",
                    "state": "inprogress",
                    "priority": "7241259335668204000",
                    "nominated": "false",
                    "bytesSent": "0",
                    "currentRoundTripTime": "NA",
                    "totalRoundTripTime": "NA",
                    "bytesReceived": "0"
                }
            },
            "inbound-rtp": {
                "3e8e63a7": {
                    "id": "3e8e63a7",
                    "timestamp": "1624451184672",
                    "ssrc": "520498122",
                    "kind": "audio",
                    "transportId": "NA",
                    "codecId": "NA",
                    "packetsReceived": "532",
                    "packetsLost": "0",
                    "packetsDiscarded": "NA",
                    "jitter": "0.002",
                    "bytesReceived": "95188",
                    "receiverId": "NA",
                    "remoteId": "70d43d81",
                    "nackCount": "0",
                    "audioLevel": "NA",
                    "framesDecoded": "NA",
                    "framesReceived": "NA",
                    "framesDropped": "NA",
                    "partialFramesLost": "NA",
                    "totalAudioEnergy": "NA",
                    "totalSamplesDuration": "NA"
                },
                "d13ac7e8": {
                    "id": "d13ac7e8",
                    "timestamp": "1624451184672",
                    "ssrc": "4223424412",
                    "kind": "video",
                    "transportId": "NA",
                    "codecId": "NA",
                    "packetsReceived": "2394",
                    "packetsLost": "0",
                    "packetsDiscarded": "NA",
                    "jitter": "0.014",
                    "bytesReceived": "2665276",
                    "receiverId": "NA",
                    "remoteId": "e0bb0faa",
                    "nackCount": "0",
                    "audioLevel": "NA",
                    "framesDecoded": "276",
                    "framesReceived": "NA",
                    "framesDropped": "NA",
                    "partialFramesLost": "NA",
                    "totalAudioEnergy": "NA",
                    "totalSamplesDuration": "NA"
                }
            },
            "local-candidate": {
                "1698ae52": {
                    "id": "1698ae52",
                    "timestamp": "1624451184671",
                    "address": "192.168.1.12",
                    "port": "57389",
                    "protocol": "udp",
                    "candidateType": "host",
                    "url": "NA"
                },
                "718e1a6f": {
                    "id": "718e1a6f",
                    "timestamp": "1624451184671",
                    "address": "2.87.64.185",
                    "port": "57389",
                    "protocol": "udp",
                    "candidateType": "srflx",
                    "url": "NA"
                },
                "59ba6e0b": {
                    "id": "59ba6e0b",
                    "timestamp": "1624451184671",
                    "address": "2a02:587:3e07:5100:e950:d005:6847:63d8",
                    "port": "57390",
                    "protocol": "udp",
                    "candidateType": "host",
                    "url": "NA"
                },
                "eb49fe10": {
                    "id": "eb49fe10",
                    "timestamp": "1624451184671",
                    "address": "192.168.1.12",
                    "port": "55528",
                    "protocol": "tcp",
                    "candidateType": "host",
                    "url": "NA"
                },
                "e0281fa6": {
                    "id": "e0281fa6",
                    "timestamp": "1624451184671",
                    "address": "2a02:587:3e07:5100:e950:d005:6847:63d8",
                    "port": "59550",
                    "protocol": "tcp",
                    "candidateType": "host",
                    "url": "NA"
                }
            },
            "outbound-rtp": {
                "436e0425": {
                    "id": "436e0425",
                    "timestamp": "1624451184671",
                    "ssrc": "3432877157",
                    "kind": "audio",
                    "transportId": "NA",
                    "codecId": "NA",
                    "packetsSent": "532",
                    "bytesSent": "44468",
                    "senderId": "NA",
                    "remoteId": "ed977358",
                    "nackCount": "0",
                    "framesEncoded": "NA",
                    "framesSent": "NA",
                    "framesPerSecond": "NA"
                },
                "8f34652c": {
                    "id": "8f34652c",
                    "timestamp": "1624451184671",
                    "ssrc": "3414702279",
                    "kind": "video",
                    "transportId": "NA",
                    "codecId": "NA",
                    "packetsSent": "2256",
                    "bytesSent": "2504072",
                    "senderId": "NA",
                    "remoteId": "c61fe2f2",
                    "nackCount": "0",
                    "framesEncoded": "286",
                    "framesSent": "NA",
                    "framesPerSecond": "NA"
                }
            },
            "remote-candidate": {
                "dfbb0ae2": {
                    "id": "dfbb0ae2",
                    "timestamp": "1624451184671",
                    "address": "192.168.1.12",
                    "port": "53417",
                    "protocol": "udp",
                    "candidateType": "host",
                    "url": "NA"
                },
                "d9b257e6": {
                    "id": "d9b257e6",
                    "timestamp": "1624451184671",
                    "address": "2a02:587:3e07:5100:e950:d005:6847:63d8",
                    "port": "57532",
                    "protocol": "udp",
                    "candidateType": "host",
                    "url": "NA"
                },
                "dcaacc16": {
                    "id": "dcaacc16",
                    "timestamp": "1624451184671",
                    "address": "2.87.64.185",
                    "port": "53417",
                    "protocol": "udp",
                    "candidateType": "srflx",
                    "url": "NA"
                }
            }
        },
        {
            "candidate-pair": {
                "b18b89bb": {
                    "id": "b18b89bb",
                    "timestamp": "1624451186715",
                    "localCandidateId": "59ba6e0b",
                    "remoteCandidateId": "d9b257e6",
                    "state": "succeeded",
                    "priority": "9115005270282359000",
                    "nominated": "true",
                    "bytesSent": "3233467",
                    "currentRoundTripTime": "NA",
                    "totalRoundTripTime": "NA",
                    "bytesReceived": "3497205"
                },
                "bb8c1d68": {
                    "id": "bb8c1d68",
                    "timestamp": "1624451186715",
                    "localCandidateId": "1698ae52",
                    "remoteCandidateId": "dfbb0ae2",
                    "state": "succeeded",
                    "priority": "9114723795305512000",
                    "nominated": "true",
                    "bytesSent": "11612",
                    "currentRoundTripTime": "NA",
                    "totalRoundTripTime": "NA",
                    "bytesReceived": "7180"
                },
                "653ab543": {
                    "id": "653ab543",
                    "timestamp": "1624451186715",
                    "localCandidateId": "1698ae52",
                    "remoteCandidateId": "dcaacc16",
                    "state": "failed",
                    "priority": "7241259335668204000",
                    "nominated": "false",
                    "bytesSent": "0",
                    "currentRoundTripTime": "NA",
                    "totalRoundTripTime": "NA",
                    "bytesReceived": "0"
                }
            },
            "inbound-rtp": {
                "3e8e63a7": {
                    "id": "3e8e63a7",
                    "timestamp": "1624451186715",
                    "ssrc": "520498122",
                    "kind": "audio",
                    "transportId": "NA",
                    "codecId": "NA",
                    "packetsReceived": "634",
                    "packetsLost": "0",
                    "packetsDiscarded": "NA",
                    "jitter": "0.002",
                    "bytesReceived": "113490",
                    "receiverId": "NA",
                    "remoteId": "70d43d81",
                    "nackCount": "0",
                    "audioLevel": "NA",
                    "framesDecoded": "NA",
                    "framesReceived": "NA",
                    "framesDropped": "NA",
                    "partialFramesLost": "NA",
                    "totalAudioEnergy": "NA",
                    "totalSamplesDuration": "NA"
                },
                "d13ac7e8": {
                    "id": "d13ac7e8",
                    "timestamp": "1624451186715",
                    "ssrc": "4223424412",
                    "kind": "video",
                    "transportId": "NA",
                    "codecId": "NA",
                    "packetsReceived": "2984",
                    "packetsLost": "0",
                    "packetsDiscarded": "NA",
                    "jitter": "0.012",
                    "bytesReceived": "3335342",
                    "receiverId": "NA",
                    "remoteId": "e0bb0faa",
                    "nackCount": "0",
                    "audioLevel": "NA",
                    "framesDecoded": "336",
                    "framesReceived": "NA",
                    "framesDropped": "NA",
                    "partialFramesLost": "NA",
                    "totalAudioEnergy": "NA",
                    "totalSamplesDuration": "NA"
                }
            },
            "local-candidate": {
                "1698ae52": {
                    "id": "1698ae52",
                    "timestamp": "1624451186715",
                    "address": "192.168.1.12",
                    "port": "57389",
                    "protocol": "udp",
                    "candidateType": "host",
                    "url": "NA"
                },
                "718e1a6f": {
                    "id": "718e1a6f",
                    "timestamp": "1624451186715",
                    "address": "2.87.64.185",
                    "port": "57389",
                    "protocol": "udp",
                    "candidateType": "srflx",
                    "url": "NA"
                },
                "59ba6e0b": {
                    "id": "59ba6e0b",
                    "timestamp": "1624451186715",
                    "address": "2a02:587:3e07:5100:e950:d005:6847:63d8",
                    "port": "57390",
                    "protocol": "udp",
                    "candidateType": "host",
                    "url": "NA"
                },
                "eb49fe10": {
                    "id": "eb49fe10",
                    "timestamp": "1624451186715",
                    "address": "192.168.1.12",
                    "port": "55528",
                    "protocol": "tcp",
                    "candidateType": "host",
                    "url": "NA"
                },
                "e0281fa6": {
                    "id": "e0281fa6",
                    "timestamp": "1624451186715",
                    "address": "2a02:587:3e07:5100:e950:d005:6847:63d8",
                    "port": "59550",
                    "protocol": "tcp",
                    "candidateType": "host",
                    "url": "NA"
                }
            },
            "outbound-rtp": {
                "436e0425": {
                    "id": "436e0425",
                    "timestamp": "1624451186715",
                    "ssrc": "3432877157",
                    "kind": "audio",
                    "transportId": "NA",
                    "codecId": "NA",
                    "packetsSent": "634",
                    "bytesSent": "53577",
                    "senderId": "NA",
                    "remoteId": "ed977358",
                    "nackCount": "0",
                    "framesEncoded": "NA",
                    "framesSent": "NA",
                    "framesPerSecond": "NA"
                },
                "8f34652c": {
                    "id": "8f34652c",
                    "timestamp": "1624451186715",
                    "ssrc": "3414702279",
                    "kind": "video",
                    "transportId": "NA",
                    "codecId": "NA",
                    "packetsSent": "2816",
                    "bytesSent": "3137159",
                    "senderId": "NA",
                    "remoteId": "c61fe2f2",
                    "nackCount": "0",
                    "framesEncoded": "346",
                    "framesSent": "NA",
                    "framesPerSecond": "NA"
                }
            },
            "remote-candidate": {
                "dfbb0ae2": {
                    "id": "dfbb0ae2",
                    "timestamp": "1624451186715",
                    "address": "192.168.1.12",
                    "port": "53417",
                    "protocol": "udp",
                    "candidateType": "host",
                    "url": "NA"
                },
                "d9b257e6": {
                    "id": "d9b257e6",
                    "timestamp": "1624451186715",
                    "address": "2a02:587:3e07:5100:e950:d005:6847:63d8",
                    "port": "57532",
                    "protocol": "udp",
                    "candidateType": "host",
                    "url": "NA"
                },
                "dcaacc16": {
                    "id": "dcaacc16",
                    "timestamp": "1624451186715",
                    "address": "2.87.64.185",
                    "port": "53417",
                    "protocol": "udp",
                    "candidateType": "srflx",
                    "url": "NA"
                }
            }
        },
        {
            "candidate-pair": {
                "b18b89bb": {
                    "id": "b18b89bb",
                    "timestamp": "1624451188762",
                    "localCandidateId": "59ba6e0b",
                    "remoteCandidateId": "d9b257e6",
                    "state": "succeeded",
                    "priority": "9115005270282359000",
                    "nominated": "true",
                    "bytesSent": "3774860",
                    "currentRoundTripTime": "NA",
                    "totalRoundTripTime": "NA",
                    "bytesReceived": "4167788"
                },
                "bb8c1d68": {
                    "id": "bb8c1d68",
                    "timestamp": "1624451188762",
                    "localCandidateId": "1698ae52",
                    "remoteCandidateId": "dfbb0ae2",
                    "state": "succeeded",
                    "priority": "9114723795305512000",
                    "nominated": "true",
                    "bytesSent": "11612",
                    "currentRoundTripTime": "NA",
                    "totalRoundTripTime": "NA",
                    "bytesReceived": "7180"
                },
                "653ab543": {
                    "id": "653ab543",
                    "timestamp": "1624451188762",
                    "localCandidateId": "1698ae52",
                    "remoteCandidateId": "dcaacc16",
                    "state": "failed",
                    "priority": "7241259335668204000",
                    "nominated": "false",
                    "bytesSent": "0",
                    "currentRoundTripTime": "NA",
                    "totalRoundTripTime": "NA",
                    "bytesReceived": "0"
                }
            },
            "inbound-rtp": {
                "3e8e63a7": {
                    "id": "3e8e63a7",
                    "timestamp": "1624451188762",
                    "ssrc": "520498122",
                    "kind": "audio",
                    "transportId": "NA",
                    "codecId": "NA",
                    "packetsReceived": "737",
                    "packetsLost": "0",
                    "packetsDiscarded": "NA",
                    "jitter": "0.002",
                    "bytesReceived": "122655",
                    "receiverId": "NA",
                    "remoteId": "70d43d81",
                    "nackCount": "0",
                    "audioLevel": "NA",
                    "framesDecoded": "NA",
                    "framesReceived": "NA",
                    "framesDropped": "NA",
                    "partialFramesLost": "NA",
                    "totalAudioEnergy": "NA",
                    "totalSamplesDuration": "NA"
                },
                "d13ac7e8": {
                    "id": "d13ac7e8",
                    "timestamp": "1624451188762",
                    "ssrc": "4223424412",
                    "kind": "video",
                    "transportId": "NA",
                    "codecId": "NA",
                    "packetsReceived": "3556",
                    "packetsLost": "0",
                    "packetsDiscarded": "NA",
                    "jitter": "0.01",
                    "bytesReceived": "3986750",
                    "receiverId": "NA",
                    "remoteId": "e0bb0faa",
                    "nackCount": "0",
                    "audioLevel": "NA",
                    "framesDecoded": "394",
                    "framesReceived": "NA",
                    "framesDropped": "NA",
                    "partialFramesLost": "NA",
                    "totalAudioEnergy": "NA",
                    "totalSamplesDuration": "NA"
                }
            },
            "local-candidate": {
                "1698ae52": {
                    "id": "1698ae52",
                    "timestamp": "1624451188762",
                    "address": "192.168.1.12",
                    "port": "57389",
                    "protocol": "udp",
                    "candidateType": "host",
                    "url": "NA"
                },
                "718e1a6f": {
                    "id": "718e1a6f",
                    "timestamp": "1624451188762",
                    "address": "2.87.64.185",
                    "port": "57389",
                    "protocol": "udp",
                    "candidateType": "srflx",
                    "url": "NA"
                },
                "59ba6e0b": {
                    "id": "59ba6e0b",
                    "timestamp": "1624451188762",
                    "address": "2a02:587:3e07:5100:e950:d005:6847:63d8",
                    "port": "57390",
                    "protocol": "udp",
                    "candidateType": "host",
                    "url": "NA"
                },
                "eb49fe10": {
                    "id": "eb49fe10",
                    "timestamp": "1624451188762",
                    "address": "192.168.1.12",
                    "port": "55528",
                    "protocol": "tcp",
                    "candidateType": "host",
                    "url": "NA"
                },
                "e0281fa6": {
                    "id": "e0281fa6",
                    "timestamp": "1624451188762",
                    "address": "2a02:587:3e07:5100:e950:d005:6847:63d8",
                    "port": "59550",
                    "protocol": "tcp",
                    "candidateType": "host",
                    "url": "NA"
                }
            },
            "outbound-rtp": {
                "436e0425": {
                    "id": "436e0425",
                    "timestamp": "1624451188762",
                    "ssrc": "3432877157",
                    "kind": "audio",
                    "transportId": "NA",
                    "codecId": "NA",
                    "packetsSent": "737",
                    "bytesSent": "64019",
                    "senderId": "NA",
                    "remoteId": "ed977358",
                    "nackCount": "0",
                    "framesEncoded": "NA",
                    "framesSent": "NA",
                    "framesPerSecond": "NA"
                },
                "8f34652c": {
                    "id": "8f34652c",
                    "timestamp": "1624451188762",
                    "ssrc": "3414702279",
                    "kind": "video",
                    "transportId": "NA",
                    "codecId": "NA",
                    "packetsSent": "3277",
                    "bytesSent": "3659400",
                    "senderId": "NA",
                    "remoteId": "c61fe2f2",
                    "nackCount": "0",
                    "framesEncoded": "405",
                    "framesSent": "NA",
                    "framesPerSecond": "NA"
                }
            },
            "remote-candidate": {
                "dfbb0ae2": {
                    "id": "dfbb0ae2",
                    "timestamp": "1624451188762",
                    "address": "192.168.1.12",
                    "port": "53417",
                    "protocol": "udp",
                    "candidateType": "host",
                    "url": "NA"
                },
                "d9b257e6": {
                    "id": "d9b257e6",
                    "timestamp": "1624451188762",
                    "address": "2a02:587:3e07:5100:e950:d005:6847:63d8",
                    "port": "57532",
                    "protocol": "udp",
                    "candidateType": "host",
                    "url": "NA"
                },
                "dcaacc16": {
                    "id": "dcaacc16",
                    "timestamp": "1624451188762",
                    "address": "2.87.64.185",
                    "port": "53417",
                    "protocol": "udp",
                    "candidateType": "srflx",
                    "url": "NA"
                }
            }
        },
        {
            "candidate-pair": {
                "b18b89bb": {
                    "id": "b18b89bb",
                    "timestamp": "1624451190809",
                    "localCandidateId": "59ba6e0b",
                    "remoteCandidateId": "d9b257e6",
                    "state": "succeeded",
                    "priority": "9115005270282359000",
                    "nominated": "true",
                    "bytesSent": "4152172",
                    "currentRoundTripTime": "NA",
                    "totalRoundTripTime": "NA",
                    "bytesReceived": "4653790"
                },
                "bb8c1d68": {
                    "id": "bb8c1d68",
                    "timestamp": "1624451190809",
                    "localCandidateId": "1698ae52",
                    "remoteCandidateId": "dfbb0ae2",
                    "state": "succeeded",
                    "priority": "9114723795305512000",
                    "nominated": "true",
                    "bytesSent": "11612",
                    "currentRoundTripTime": "NA",
                    "totalRoundTripTime": "NA",
                    "bytesReceived": "7180"
                },
                "653ab543": {
                    "id": "653ab543",
                    "timestamp": "1624451190809",
                    "localCandidateId": "1698ae52",
                    "remoteCandidateId": "dcaacc16",
                    "state": "failed",
                    "priority": "7241259335668204000",
                    "nominated": "false",
                    "bytesSent": "0",
                    "currentRoundTripTime": "NA",
                    "totalRoundTripTime": "NA",
                    "bytesReceived": "0"
                }
            },
            "inbound-rtp": {
                "3e8e63a7": {
                    "id": "3e8e63a7",
                    "timestamp": "1624451190809",
                    "ssrc": "520498122",
                    "kind": "audio",
                    "transportId": "NA",
                    "codecId": "NA",
                    "packetsReceived": "839",
                    "packetsLost": "0",
                    "packetsDiscarded": "NA",
                    "jitter": "0.002",
                    "bytesReceived": "125635",
                    "receiverId": "NA",
                    "remoteId": "70d43d81",
                    "nackCount": "0",
                    "audioLevel": "NA",
                    "framesDecoded": "NA",
                    "framesReceived": "NA",
                    "framesDropped": "NA",
                    "partialFramesLost": "NA",
                    "totalAudioEnergy": "NA",
                    "totalSamplesDuration": "NA"
                },
                "d13ac7e8": {
                    "id": "d13ac7e8",
                    "timestamp": "1624451190809",
                    "ssrc": "4223424412",
                    "kind": "video",
                    "transportId": "NA",
                    "codecId": "NA",
                    "packetsReceived": "3989",
                    "packetsLost": "0",
                    "packetsDiscarded": "NA",
                    "jitter": "0.012",
                    "bytesReceived": "4461764",
                    "receiverId": "NA",
                    "remoteId": "e0bb0faa",
                    "nackCount": "0",
                    "audioLevel": "NA",
                    "framesDecoded": "456",
                    "framesReceived": "NA",
                    "framesDropped": "NA",
                    "partialFramesLost": "NA",
                    "totalAudioEnergy": "NA",
                    "totalSamplesDuration": "NA"
                }
            },
            "local-candidate": {
                "1698ae52": {
                    "id": "1698ae52",
                    "timestamp": "1624451190809",
                    "address": "192.168.1.12",
                    "port": "57389",
                    "protocol": "udp",
                    "candidateType": "host",
                    "url": "NA"
                },
                "718e1a6f": {
                    "id": "718e1a6f",
                    "timestamp": "1624451190809",
                    "address": "2.87.64.185",
                    "port": "57389",
                    "protocol": "udp",
                    "candidateType": "srflx",
                    "url": "NA"
                },
                "59ba6e0b": {
                    "id": "59ba6e0b",
                    "timestamp": "1624451190809",
                    "address": "2a02:587:3e07:5100:e950:d005:6847:63d8",
                    "port": "57390",
                    "protocol": "udp",
                    "candidateType": "host",
                    "url": "NA"
                },
                "eb49fe10": {
                    "id": "eb49fe10",
                    "timestamp": "1624451190809",
                    "address": "192.168.1.12",
                    "port": "55528",
                    "protocol": "tcp",
                    "candidateType": "host",
                    "url": "NA"
                },
                "e0281fa6": {
                    "id": "e0281fa6",
                    "timestamp": "1624451190809",
                    "address": "2a02:587:3e07:5100:e950:d005:6847:63d8",
                    "port": "59550",
                    "protocol": "tcp",
                    "candidateType": "host",
                    "url": "NA"
                }
            },
            "outbound-rtp": {
                "436e0425": {
                    "id": "436e0425",
                    "timestamp": "1624451190809",
                    "ssrc": "3432877157",
                    "kind": "audio",
                    "transportId": "NA",
                    "codecId": "NA",
                    "packetsSent": "839",
                    "bytesSent": "74345",
                    "senderId": "NA",
                    "remoteId": "ed977358",
                    "nackCount": "0",
                    "framesEncoded": "NA",
                    "framesSent": "NA",
                    "framesPerSecond": "NA"
                },
                "8f34652c": {
                    "id": "8f34652c",
                    "timestamp": "1624451190809",
                    "ssrc": "3414702279",
                    "kind": "video",
                    "transportId": "NA",
                    "codecId": "NA",
                    "packetsSent": "3613",
                    "bytesSent": "4019418",
                    "senderId": "NA",
                    "remoteId": "c61fe2f2",
                    "nackCount": "0",
                    "framesEncoded": "464",
                    "framesSent": "NA",
                    "framesPerSecond": "NA"
                }
            },
            "remote-candidate": {
                "dfbb0ae2": {
                    "id": "dfbb0ae2",
                    "timestamp": "1624451190809",
                    "address": "192.168.1.12",
                    "port": "53417",
                    "protocol": "udp",
                    "candidateType": "host",
                    "url": "NA"
                },
                "d9b257e6": {
                    "id": "d9b257e6",
                    "timestamp": "1624451190809",
                    "address": "2a02:587:3e07:5100:e950:d005:6847:63d8",
                    "port": "57532",
                    "protocol": "udp",
                    "candidateType": "host",
                    "url": "NA"
                },
                "dcaacc16": {
                    "id": "dcaacc16",
                    "timestamp": "1624451190809",
                    "address": "2.87.64.185",
                    "port": "53417",
                    "protocol": "udp",
                    "candidateType": "srflx",
                    "url": "NA"
                }
            }
        },
        {
            "candidate-pair": {
                "b18b89bb": {
                    "id": "b18b89bb",
                    "timestamp": "1624451192853",
                    "localCandidateId": "59ba6e0b",
                    "remoteCandidateId": "d9b257e6",
                    "state": "succeeded",
                    "priority": "9115005270282359000",
                    "nominated": "true",
                    "bytesSent": "4741543",
                    "currentRoundTripTime": "NA",
                    "totalRoundTripTime": "NA",
                    "bytesReceived": "5273652"
                },
                "bb8c1d68": {
                    "id": "bb8c1d68",
                    "timestamp": "1624451192853",
                    "localCandidateId": "1698ae52",
                    "remoteCandidateId": "dfbb0ae2",
                    "state": "succeeded",
                    "priority": "9114723795305512000",
                    "nominated": "true",
                    "bytesSent": "11612",
                    "currentRoundTripTime": "NA",
                    "totalRoundTripTime": "NA",
                    "bytesReceived": "7180"
                },
                "653ab543": {
                    "id": "653ab543",
                    "timestamp": "1624451192853",
                    "localCandidateId": "1698ae52",
                    "remoteCandidateId": "dcaacc16",
                    "state": "failed",
                    "priority": "7241259335668204000",
                    "nominated": "false",
                    "bytesSent": "0",
                    "currentRoundTripTime": "NA",
                    "totalRoundTripTime": "NA",
                    "bytesReceived": "0"
                }
            },
            "inbound-rtp": {
                "3e8e63a7": {
                    "id": "3e8e63a7",
                    "timestamp": "1624451192853",
                    "ssrc": "520498122",
                    "kind": "audio",
                    "transportId": "NA",
                    "codecId": "NA",
                    "packetsReceived": "941",
                    "packetsLost": "0",
                    "packetsDiscarded": "NA",
                    "jitter": "0.002",
                    "bytesReceived": "133831",
                    "receiverId": "NA",
                    "remoteId": "70d43d81",
                    "nackCount": "0",
                    "audioLevel": "NA",
                    "framesDecoded": "NA",
                    "framesReceived": "NA",
                    "framesDropped": "NA",
                    "partialFramesLost": "NA",
                    "totalAudioEnergy": "NA",
                    "totalSamplesDuration": "NA"
                },
                "d13ac7e8": {
                    "id": "d13ac7e8",
                    "timestamp": "1624451192854",
                    "ssrc": "4223424412",
                    "kind": "video",
                    "transportId": "NA",
                    "codecId": "NA",
                    "packetsReceived": "4517",
                    "packetsLost": "0",
                    "packetsDiscarded": "NA",
                    "jitter": "0.015",
                    "bytesReceived": "5064070",
                    "receiverId": "NA",
                    "remoteId": "e0bb0faa",
                    "nackCount": "0",
                    "audioLevel": "NA",
                    "framesDecoded": "512",
                    "framesReceived": "NA",
                    "framesDropped": "NA",
                    "partialFramesLost": "NA",
                    "totalAudioEnergy": "NA",
                    "totalSamplesDuration": "NA"
                }
            },
            "local-candidate": {
                "1698ae52": {
                    "id": "1698ae52",
                    "timestamp": "1624451192853",
                    "address": "192.168.1.12",
                    "port": "57389",
                    "protocol": "udp",
                    "candidateType": "host",
                    "url": "NA"
                },
                "718e1a6f": {
                    "id": "718e1a6f",
                    "timestamp": "1624451192853",
                    "address": "2.87.64.185",
                    "port": "57389",
                    "protocol": "udp",
                    "candidateType": "srflx",
                    "url": "NA"
                },
                "59ba6e0b": {
                    "id": "59ba6e0b",
                    "timestamp": "1624451192853",
                    "address": "2a02:587:3e07:5100:e950:d005:6847:63d8",
                    "port": "57390",
                    "protocol": "udp",
                    "candidateType": "host",
                    "url": "NA"
                },
                "eb49fe10": {
                    "id": "eb49fe10",
                    "timestamp": "1624451192853",
                    "address": "192.168.1.12",
                    "port": "55528",
                    "protocol": "tcp",
                    "candidateType": "host",
                    "url": "NA"
                },
                "e0281fa6": {
                    "id": "e0281fa6",
                    "timestamp": "1624451192853",
                    "address": "2a02:587:3e07:5100:e950:d005:6847:63d8",
                    "port": "59550",
                    "protocol": "tcp",
                    "candidateType": "host",
                    "url": "NA"
                }
            },
            "outbound-rtp": {
                "436e0425": {
                    "id": "436e0425",
                    "timestamp": "1624451192853",
                    "ssrc": "3432877157",
                    "kind": "audio",
                    "transportId": "NA",
                    "codecId": "NA",
                    "packetsSent": "941",
                    "bytesSent": "84647",
                    "senderId": "NA",
                    "remoteId": "ed977358",
                    "nackCount": "0",
                    "framesEncoded": "NA",
                    "framesSent": "NA",
                    "framesPerSecond": "NA"
                },
                "8f34652c": {
                    "id": "8f34652c",
                    "timestamp": "1624451192853",
                    "ssrc": "3414702279",
                    "kind": "video",
                    "transportId": "NA",
                    "codecId": "NA",
                    "packetsSent": "4119",
                    "bytesSent": "4589123",
                    "senderId": "NA",
                    "remoteId": "c61fe2f2",
                    "nackCount": "0",
                    "framesEncoded": "523",
                    "framesSent": "NA",
                    "framesPerSecond": "NA"
                }
            },
            "remote-candidate": {
                "dfbb0ae2": {
                    "id": "dfbb0ae2",
                    "timestamp": "1624451192853",
                    "address": "192.168.1.12",
                    "port": "53417",
                    "protocol": "udp",
                    "candidateType": "host",
                    "url": "NA"
                },
                "d9b257e6": {
                    "id": "d9b257e6",
                    "timestamp": "1624451192853",
                    "address": "2a02:587:3e07:5100:e950:d005:6847:63d8",
                    "port": "57532",
                    "protocol": "udp",
                    "candidateType": "host",
                    "url": "NA"
                },
                "dcaacc16": {
                    "id": "dcaacc16",
                    "timestamp": "1624451192853",
                    "address": "2.87.64.185",
                    "port": "53417",
                    "protocol": "udp",
                    "candidateType": "srflx",
                    "url": "NA"
                }
            }
        },
        {
            "candidate-pair": {
                "b18b89bb": {
                    "id": "b18b89bb",
                    "timestamp": "1624451194898",
                    "localCandidateId": "59ba6e0b",
                    "remoteCandidateId": "d9b257e6",
                    "state": "succeeded",
                    "priority": "9115005270282359000",
                    "nominated": "true",
                    "bytesSent": "5287609",
                    "currentRoundTripTime": "NA",
                    "totalRoundTripTime": "NA",
                    "bytesReceived": "5990948"
                },
                "bb8c1d68": {
                    "id": "bb8c1d68",
                    "timestamp": "1624451194898",
                    "localCandidateId": "1698ae52",
                    "remoteCandidateId": "dfbb0ae2",
                    "state": "succeeded",
                    "priority": "9114723795305512000",
                    "nominated": "true",
                    "bytesSent": "11612",
                    "currentRoundTripTime": "NA",
                    "totalRoundTripTime": "NA",
                    "bytesReceived": "7180"
                },
                "653ab543": {
                    "id": "653ab543",
                    "timestamp": "1624451194898",
                    "localCandidateId": "1698ae52",
                    "remoteCandidateId": "dcaacc16",
                    "state": "failed",
                    "priority": "7241259335668204000",
                    "nominated": "false",
                    "bytesSent": "0",
                    "currentRoundTripTime": "NA",
                    "totalRoundTripTime": "NA",
                    "bytesReceived": "0"
                }
            },
            "inbound-rtp": {
                "3e8e63a7": {
                    "id": "3e8e63a7",
                    "timestamp": "1624451194898",
                    "ssrc": "520498122",
                    "kind": "audio",
                    "transportId": "NA",
                    "codecId": "NA",
                    "packetsReceived": "1043",
                    "packetsLost": "0",
                    "packetsDiscarded": "NA",
                    "jitter": "0.002",
                    "bytesReceived": "142734",
                    "receiverId": "NA",
                    "remoteId": "70d43d81",
                    "nackCount": "0",
                    "audioLevel": "NA",
                    "framesDecoded": "NA",
                    "framesReceived": "NA",
                    "framesDropped": "NA",
                    "partialFramesLost": "NA",
                    "totalAudioEnergy": "NA",
                    "totalSamplesDuration": "NA"
                },
                "d13ac7e8": {
                    "id": "d13ac7e8",
                    "timestamp": "1624451194898",
                    "ssrc": "4223424412",
                    "kind": "video",
                    "transportId": "NA",
                    "codecId": "NA",
                    "packetsReceived": "5130",
                    "packetsLost": "0",
                    "packetsDiscarded": "NA",
                    "jitter": "0.013",
                    "bytesReceived": "5762137",
                    "receiverId": "NA",
                    "remoteId": "e0bb0faa",
                    "nackCount": "0",
                    "audioLevel": "NA",
                    "framesDecoded": "601",
                    "framesReceived": "NA",
                    "framesDropped": "NA",
                    "partialFramesLost": "NA",
                    "totalAudioEnergy": "NA",
                    "totalSamplesDuration": "NA"
                }
            },
            "local-candidate": {
                "1698ae52": {
                    "id": "1698ae52",
                    "timestamp": "1624451194898",
                    "address": "192.168.1.12",
                    "port": "57389",
                    "protocol": "udp",
                    "candidateType": "host",
                    "url": "NA"
                },
                "718e1a6f": {
                    "id": "718e1a6f",
                    "timestamp": "1624451194898",
                    "address": "2.87.64.185",
                    "port": "57389",
                    "protocol": "udp",
                    "candidateType": "srflx",
                    "url": "NA"
                },
                "59ba6e0b": {
                    "id": "59ba6e0b",
                    "timestamp": "1624451194898",
                    "address": "2a02:587:3e07:5100:e950:d005:6847:63d8",
                    "port": "57390",
                    "protocol": "udp",
                    "candidateType": "host",
                    "url": "NA"
                },
                "eb49fe10": {
                    "id": "eb49fe10",
                    "timestamp": "1624451194898",
                    "address": "192.168.1.12",
                    "port": "55528",
                    "protocol": "tcp",
                    "candidateType": "host",
                    "url": "NA"
                },
                "e0281fa6": {
                    "id": "e0281fa6",
                    "timestamp": "1624451194898",
                    "address": "2a02:587:3e07:5100:e950:d005:6847:63d8",
                    "port": "59550",
                    "protocol": "tcp",
                    "candidateType": "host",
                    "url": "NA"
                }
            },
            "outbound-rtp": {
                "436e0425": {
                    "id": "436e0425",
                    "timestamp": "1624451194898",
                    "ssrc": "3432877157",
                    "kind": "audio",
                    "transportId": "NA",
                    "codecId": "NA",
                    "packetsSent": "1043",
                    "bytesSent": "94897",
                    "senderId": "NA",
                    "remoteId": "ed977358",
                    "nackCount": "0",
                    "framesEncoded": "NA",
                    "framesSent": "NA",
                    "framesPerSecond": "NA"
                },
                "8f34652c": {
                    "id": "8f34652c",
                    "timestamp": "1624451194898",
                    "ssrc": "3414702279",
                    "kind": "video",
                    "transportId": "NA",
                    "codecId": "NA",
                    "packetsSent": "4589",
                    "bytesSent": "5115889",
                    "senderId": "NA",
                    "remoteId": "c61fe2f2",
                    "nackCount": "0",
                    "framesEncoded": "615",
                    "framesSent": "NA",
                    "framesPerSecond": "NA"
                }
            },
            "remote-candidate": {
                "dfbb0ae2": {
                    "id": "dfbb0ae2",
                    "timestamp": "1624451194898",
                    "address": "192.168.1.12",
                    "port": "53417",
                    "protocol": "udp",
                    "candidateType": "host",
                    "url": "NA"
                },
                "d9b257e6": {
                    "id": "d9b257e6",
                    "timestamp": "1624451194898",
                    "address": "2a02:587:3e07:5100:e950:d005:6847:63d8",
                    "port": "57532",
                    "protocol": "udp",
                    "candidateType": "host",
                    "url": "NA"
                },
                "dcaacc16": {
                    "id": "dcaacc16",
                    "timestamp": "1624451194898",
                    "address": "2.87.64.185",
                    "port": "53417",
                    "protocol": "udp",
                    "candidateType": "srflx",
                    "url": "NA"
                }
            }
        },
        {
            "candidate-pair": {
                "b18b89bb": {
                    "id": "b18b89bb",
                    "timestamp": "1624451196945",
                    "localCandidateId": "59ba6e0b",
                    "remoteCandidateId": "d9b257e6",
                    "state": "succeeded",
                    "priority": "9115005270282359000",
                    "nominated": "true",
                    "bytesSent": "5831428",
                    "currentRoundTripTime": "NA",
                    "totalRoundTripTime": "NA",
                    "bytesReceived": "6642718"
                },
                "bb8c1d68": {
                    "id": "bb8c1d68",
                    "timestamp": "1624451196945",
                    "localCandidateId": "1698ae52",
                    "remoteCandidateId": "dfbb0ae2",
                    "state": "succeeded",
                    "priority": "9114723795305512000",
                    "nominated": "true",
                    "bytesSent": "11612",
                    "currentRoundTripTime": "NA",
                    "totalRoundTripTime": "NA",
                    "bytesReceived": "7180"
                },
                "653ab543": {
                    "id": "653ab543",
                    "timestamp": "1624451196945",
                    "localCandidateId": "1698ae52",
                    "remoteCandidateId": "dcaacc16",
                    "state": "failed",
                    "priority": "7241259335668204000",
                    "nominated": "false",
                    "bytesSent": "0",
                    "currentRoundTripTime": "NA",
                    "totalRoundTripTime": "NA",
                    "bytesReceived": "0"
                }
            },
            "inbound-rtp": {
                "3e8e63a7": {
                    "id": "3e8e63a7",
                    "timestamp": "1624451196945",
                    "ssrc": "520498122",
                    "kind": "audio",
                    "transportId": "NA",
                    "codecId": "NA",
                    "packetsReceived": "1146",
                    "packetsLost": "0",
                    "packetsDiscarded": "NA",
                    "jitter": "0.002",
                    "bytesReceived": "155181",
                    "receiverId": "NA",
                    "remoteId": "70d43d81",
                    "nackCount": "0",
                    "audioLevel": "NA",
                    "framesDecoded": "NA",
                    "framesReceived": "NA",
                    "framesDropped": "NA",
                    "partialFramesLost": "NA",
                    "totalAudioEnergy": "NA",
                    "totalSamplesDuration": "NA"
                },
                "d13ac7e8": {
                    "id": "d13ac7e8",
                    "timestamp": "1624451196945",
                    "ssrc": "4223424412",
                    "kind": "video",
                    "transportId": "NA",
                    "codecId": "NA",
                    "packetsReceived": "5685",
                    "packetsLost": "0",
                    "packetsDiscarded": "NA",
                    "jitter": "0.011",
                    "bytesReceived": "6391876",
                    "receiverId": "NA",
                    "remoteId": "e0bb0faa",
                    "nackCount": "0",
                    "audioLevel": "NA",
                    "framesDecoded": "659",
                    "framesReceived": "NA",
                    "framesDropped": "NA",
                    "partialFramesLost": "NA",
                    "totalAudioEnergy": "NA",
                    "totalSamplesDuration": "NA"
                }
            },
            "local-candidate": {
                "1698ae52": {
                    "id": "1698ae52",
                    "timestamp": "1624451196945",
                    "address": "192.168.1.12",
                    "port": "57389",
                    "protocol": "udp",
                    "candidateType": "host",
                    "url": "NA"
                },
                "718e1a6f": {
                    "id": "718e1a6f",
                    "timestamp": "1624451196945",
                    "address": "2.87.64.185",
                    "port": "57389",
                    "protocol": "udp",
                    "candidateType": "srflx",
                    "url": "NA"
                },
                "59ba6e0b": {
                    "id": "59ba6e0b",
                    "timestamp": "1624451196945",
                    "address": "2a02:587:3e07:5100:e950:d005:6847:63d8",
                    "port": "57390",
                    "protocol": "udp",
                    "candidateType": "host",
                    "url": "NA"
                },
                "eb49fe10": {
                    "id": "eb49fe10",
                    "timestamp": "1624451196945",
                    "address": "192.168.1.12",
                    "port": "55528",
                    "protocol": "tcp",
                    "candidateType": "host",
                    "url": "NA"
                },
                "e0281fa6": {
                    "id": "e0281fa6",
                    "timestamp": "1624451196945",
                    "address": "2a02:587:3e07:5100:e950:d005:6847:63d8",
                    "port": "59550",
                    "protocol": "tcp",
                    "candidateType": "host",
                    "url": "NA"
                }
            },
            "outbound-rtp": {
                "436e0425": {
                    "id": "436e0425",
                    "timestamp": "1624451196945",
                    "ssrc": "3432877157",
                    "kind": "audio",
                    "transportId": "NA",
                    "codecId": "NA",
                    "packetsSent": "1146",
                    "bytesSent": "105272",
                    "senderId": "NA",
                    "remoteId": "ed977358",
                    "nackCount": "0",
                    "framesEncoded": "NA",
                    "framesSent": "NA",
                    "framesPerSecond": "NA"
                },
                "8f34652c": {
                    "id": "8f34652c",
                    "timestamp": "1624451196945",
                    "ssrc": "3414702279",
                    "kind": "video",
                    "transportId": "NA",
                    "codecId": "NA",
                    "packetsSent": "5059",
                    "bytesSent": "5640331",
                    "senderId": "NA",
                    "remoteId": "c61fe2f2",
                    "nackCount": "0",
                    "framesEncoded": "674",
                    "framesSent": "NA",
                    "framesPerSecond": "NA"
                }
            },
            "remote-candidate": {
                "dfbb0ae2": {
                    "id": "dfbb0ae2",
                    "timestamp": "1624451196945",
                    "address": "192.168.1.12",
                    "port": "53417",
                    "protocol": "udp",
                    "candidateType": "host",
                    "url": "NA"
                },
                "d9b257e6": {
                    "id": "d9b257e6",
                    "timestamp": "1624451196945",
                    "address": "2a02:587:3e07:5100:e950:d005:6847:63d8",
                    "port": "57532",
                    "protocol": "udp",
                    "candidateType": "host",
                    "url": "NA"
                },
                "dcaacc16": {
                    "id": "dcaacc16",
                    "timestamp": "1624451196945",
                    "address": "2.87.64.185",
                    "port": "53417",
                    "protocol": "udp",
                    "candidateType": "srflx",
                    "url": "NA"
                }
            }
        }
    ],
    "Network Profile": "",
    "Region Id": "NC",
    "Itinerary": "0"
}