
{
    "Connected": true,
    "Room": "https://appr.tc/r/8444804535217249680",
    "StatsArray": [
        {
            "candidate-pair": {
                "ba3532b9": {
                    "id": "ba3532b9",
                    "timestamp": "1624453047795",
                    "localCandidateId": "478d454a",
                    "remoteCandidateId": "156115ba",
                    "state": "succeeded",
                    "priority": "9115005270282359000",
                    "nominated": "true",
                    "bytesSent": "480673",
                    "currentRoundTripTime": "NA",
                    "totalRoundTripTime": "NA",
                    "bytesReceived": "412733"
                },
                "6bc58b3a": {
                    "id": "6bc58b3a",
                    "timestamp": "1624453047795",
                    "localCandidateId": "6473c45f",
                    "remoteCandidateId": "e619ce5d",
                    "state": "succeeded",
                    "priority": "9114723795305512000",
                    "nominated": "true",
                    "bytesSent": "12901",
                    "currentRoundTripTime": "NA",
                    "totalRoundTripTime": "NA",
                    "bytesReceived": "7484"
                },
                "7c41d8fd": {
                    "id": "7c41d8fd",
                    "timestamp": "1624453047795",
                    "localCandidateId": "6473c45f",
                    "remoteCandidateId": "c51191fe",
                    "state": "inprogress",
                    "priority": "7241259335668204000",
                    "nominated": "false",
                    "bytesSent": "0",
                    "currentRoundTripTime": "NA",
                    "totalRoundTripTime": "NA",
                    "bytesReceived": "0"
                }
            },
            "inbound-rtp": {
                "ad295e29": {
                    "id": "ad295e29",
                    "timestamp": "1624453047795",
                    "ssrc": "3764986905",
                    "kind": "audio",
                    "transportId": "NA",
                    "codecId": "NA",
                    "packetsReceived": "124",
                    "packetsLost": "0",
                    "packetsDiscarded": "NA",
                    "jitter": "0",
                    "bytesReceived": "22444",
                    "receiverId": "NA",
                    "remoteId": "79d9e6e1",
                    "nackCount": "0",
                    "audioLevel": "NA",
                    "framesDecoded": "NA",
                    "framesReceived": "NA",
                    "framesDropped": "NA",
                    "partialFramesLost": "NA",
                    "totalAudioEnergy": "NA",
                    "totalSamplesDuration": "NA"
                },
                "3b21103f": {
                    "id": "3b21103f",
                    "timestamp": "1624453047795",
                    "ssrc": "1010522682",
                    "kind": "video",
                    "transportId": "NA",
                    "codecId": "NA",
                    "packetsReceived": "375",
                    "packetsLost": "0",
                    "packetsDiscarded": "NA",
                    "jitter": "0.028",
                    "bytesReceived": "388374",
                    "receiverId": "NA",
                    "remoteId": "1d615bea",
                    "nackCount": "0",
                    "audioLevel": "NA",
                    "framesDecoded": "43",
                    "framesReceived": "NA",
                    "framesDropped": "NA",
                    "partialFramesLost": "NA",
                    "totalAudioEnergy": "NA",
                    "totalSamplesDuration": "NA"
                }
            },
            "local-candidate": {
                "6473c45f": {
                    "id": "6473c45f",
                    "timestamp": "1624453047795",
                    "address": "192.168.1.12",
                    "port": "64379",
                    "protocol": "udp",
                    "candidateType": "host",
                    "url": "NA"
                },
                "35c1086c": {
                    "id": "35c1086c",
                    "timestamp": "1624453047795",
                    "address": "2.87.64.185",
                    "port": "64379",
                    "protocol": "udp",
                    "candidateType": "srflx",
                    "url": "NA"
                },
                "478d454a": {
                    "id": "478d454a",
                    "timestamp": "1624453047795",
                    "address": "2a02:587:3e07:5100:e950:d005:6847:63d8",
                    "port": "64380",
                    "protocol": "udp",
                    "candidateType": "host",
                    "url": "NA"
                },
                "aaa35c97": {
                    "id": "aaa35c97",
                    "timestamp": "1624453047795",
                    "address": "192.168.1.12",
                    "port": "56470",
                    "protocol": "tcp",
                    "candidateType": "host",
                    "url": "NA"
                },
                "743313ea": {
                    "id": "743313ea",
                    "timestamp": "1624453047795",
                    "address": "2a02:587:3e07:5100:e950:d005:6847:63d8",
                    "port": "52435",
                    "protocol": "tcp",
                    "candidateType": "host",
                    "url": "NA"
                }
            },
            "outbound-rtp": {
                "409f246b": {
                    "id": "409f246b",
                    "timestamp": "1624453047795",
                    "ssrc": "428917593",
                    "kind": "audio",
                    "transportId": "NA",
                    "codecId": "NA",
                    "packetsSent": "124",
                    "bytesSent": "12524",
                    "senderId": "NA",
                    "remoteId": "NA",
                    "nackCount": "0",
                    "framesEncoded": "NA",
                    "framesSent": "NA",
                    "framesPerSecond": "NA"
                },
                "ef7b79ec": {
                    "id": "ef7b79ec",
                    "timestamp": "1624453047795",
                    "ssrc": "2069049216",
                    "kind": "video",
                    "transportId": "NA",
                    "codecId": "NA",
                    "packetsSent": "440",
                    "bytesSent": "471450",
                    "senderId": "NA",
                    "remoteId": "f8f6730d",
                    "nackCount": "0",
                    "framesEncoded": "50",
                    "framesSent": "NA",
                    "framesPerSecond": "NA"
                }
            },
            "remote-candidate": {
                "e619ce5d": {
                    "id": "e619ce5d",
                    "timestamp": "1624453047795",
                    "address": "192.168.1.12",
                    "port": "56644",
                    "protocol": "udp",
                    "candidateType": "host",
                    "url": "NA"
                },
                "156115ba": {
                    "id": "156115ba",
                    "timestamp": "1624453047795",
                    "address": "2a02:587:3e07:5100:e950:d005:6847:63d8",
                    "port": "49459",
                    "protocol": "udp",
                    "candidateType": "host",
                    "url": "NA"
                },
                "c51191fe": {
                    "id": "c51191fe",
                    "timestamp": "1624453047795",
                    "address": "2.87.64.185",
                    "port": "56644",
                    "protocol": "udp",
                    "candidateType": "srflx",
                    "url": "NA"
                }
            }
        },
        {
            "candidate-pair": {
                "ba3532b9": {
                    "id": "ba3532b9",
                    "timestamp": "1624453049861",
                    "localCandidateId": "478d454a",
                    "remoteCandidateId": "156115ba",
                    "state": "succeeded",
                    "priority": "9115005270282359000",
                    "nominated": "true",
                    "bytesSent": "1060336",
                    "currentRoundTripTime": "NA",
                    "totalRoundTripTime": "NA",
                    "bytesReceived": "840835"
                },
                "6bc58b3a": {
                    "id": "6bc58b3a",
                    "timestamp": "1624453049861",
                    "localCandidateId": "6473c45f",
                    "remoteCandidateId": "e619ce5d",
                    "state": "succeeded",
                    "priority": "9114723795305512000",
                    "nominated": "true",
                    "bytesSent": "12901",
                    "currentRoundTripTime": "NA",
                    "totalRoundTripTime": "NA",
                    "bytesReceived": "7484"
                },
                "7c41d8fd": {
                    "id": "7c41d8fd",
                    "timestamp": "1624453049861",
                    "localCandidateId": "6473c45f",
                    "remoteCandidateId": "c51191fe",
                    "state": "inprogress",
                    "priority": "7241259335668204000",
                    "nominated": "false",
                    "bytesSent": "0",
                    "currentRoundTripTime": "NA",
                    "totalRoundTripTime": "NA",
                    "bytesReceived": "0"
                }
            },
            "inbound-rtp": {
                "ad295e29": {
                    "id": "ad295e29",
                    "timestamp": "1624453049861",
                    "ssrc": "3764986905",
                    "kind": "audio",
                    "transportId": "NA",
                    "codecId": "NA",
                    "packetsReceived": "228",
                    "packetsLost": "0",
                    "packetsDiscarded": "NA",
                    "jitter": "0",
                    "bytesReceived": "41428",
                    "receiverId": "NA",
                    "remoteId": "79d9e6e1",
                    "nackCount": "0",
                    "audioLevel": "NA",
                    "framesDecoded": "NA",
                    "framesReceived": "NA",
                    "framesDropped": "NA",
                    "partialFramesLost": "NA",
                    "totalAudioEnergy": "NA",
                    "totalSamplesDuration": "NA"
                },
                "3b21103f": {
                    "id": "3b21103f",
                    "timestamp": "1624453049861",
                    "ssrc": "1010522682",
                    "kind": "video",
                    "transportId": "NA",
                    "codecId": "NA",
                    "packetsReceived": "736",
                    "packetsLost": "0",
                    "packetsDiscarded": "NA",
                    "jitter": "0.022",
                    "bytesReceived": "789488",
                    "receiverId": "NA",
                    "remoteId": "1d615bea",
                    "nackCount": "0",
                    "audioLevel": "NA",
                    "framesDecoded": "96",
                    "framesReceived": "NA",
                    "framesDropped": "NA",
                    "partialFramesLost": "NA",
                    "totalAudioEnergy": "NA",
                    "totalSamplesDuration": "NA"
                }
            },
            "local-candidate": {
                "6473c45f": {
                    "id": "6473c45f",
                    "timestamp": "1624453049861",
                    "address": "192.168.1.12",
                    "port": "64379",
                    "protocol": "udp",
                    "candidateType": "host",
                    "url": "NA"
                },
                "35c1086c": {
                    "id": "35c1086c",
                    "timestamp": "1624453049861",
                    "address": "2.87.64.185",
                    "port": "64379",
                    "protocol": "udp",
                    "candidateType": "srflx",
                    "url": "NA"
                },
                "478d454a": {
                    "id": "478d454a",
                    "timestamp": "1624453049861",
                    "address": "2a02:587:3e07:5100:e950:d005:6847:63d8",
                    "port": "64380",
                    "protocol": "udp",
                    "candidateType": "host",
                    "url": "NA"
                },
                "aaa35c97": {
                    "id": "aaa35c97",
                    "timestamp": "1624453049861",
                    "address": "192.168.1.12",
                    "port": "56470",
                    "protocol": "tcp",
                    "candidateType": "host",
                    "url": "NA"
                },
                "743313ea": {
                    "id": "743313ea",
                    "timestamp": "1624453049861",
                    "address": "2a02:587:3e07:5100:e950:d005:6847:63d8",
                    "port": "52435",
                    "protocol": "tcp",
                    "candidateType": "host",
                    "url": "NA"
                }
            },
            "outbound-rtp": {
                "409f246b": {
                    "id": "409f246b",
                    "timestamp": "1624453049861",
                    "ssrc": "428917593",
                    "kind": "audio",
                    "transportId": "NA",
                    "codecId": "NA",
                    "packetsSent": "227",
                    "bytesSent": "22988",
                    "senderId": "NA",
                    "remoteId": "NA",
                    "nackCount": "0",
                    "framesEncoded": "NA",
                    "framesSent": "NA",
                    "framesPerSecond": "NA"
                },
                "ef7b79ec": {
                    "id": "ef7b79ec",
                    "timestamp": "1624453049861",
                    "ssrc": "2069049216",
                    "kind": "video",
                    "transportId": "NA",
                    "codecId": "NA",
                    "packetsSent": "934",
                    "bytesSent": "1031773",
                    "senderId": "NA",
                    "remoteId": "f8f6730d",
                    "nackCount": "0",
                    "framesEncoded": "111",
                    "framesSent": "NA",
                    "framesPerSecond": "NA"
                }
            },
            "remote-candidate": {
                "e619ce5d": {
                    "id": "e619ce5d",
                    "timestamp": "1624453049861",
                    "address": "192.168.1.12",
                    "port": "56644",
                    "protocol": "udp",
                    "candidateType": "host",
                    "url": "NA"
                },
                "156115ba": {
                    "id": "156115ba",
                    "timestamp": "1624453049861",
                    "address": "2a02:587:3e07:5100:e950:d005:6847:63d8",
                    "port": "49459",
                    "protocol": "udp",
                    "candidateType": "host",
                    "url": "NA"
                },
                "c51191fe": {
                    "id": "c51191fe",
                    "timestamp": "1624453049861",
                    "address": "2.87.64.185",
                    "port": "56644",
                    "protocol": "udp",
                    "candidateType": "srflx",
                    "url": "NA"
                }
            }
        },
        {
            "candidate-pair": {
                "ba3532b9": {
                    "id": "ba3532b9",
                    "timestamp": "1624453051926",
                    "localCandidateId": "478d454a",
                    "remoteCandidateId": "156115ba",
                    "state": "succeeded",
                    "priority": "9115005270282359000",
                    "nominated": "true",
                    "bytesSent": "1629248",
                    "currentRoundTripTime": "NA",
                    "totalRoundTripTime": "NA",
                    "bytesReceived": "1454052"
                },
                "6bc58b3a": {
                    "id": "6bc58b3a",
                    "timestamp": "1624453051926",
                    "localCandidateId": "6473c45f",
                    "remoteCandidateId": "e619ce5d",
                    "state": "succeeded",
                    "priority": "9114723795305512000",
                    "nominated": "true",
                    "bytesSent": "12901",
                    "currentRoundTripTime": "NA",
                    "totalRoundTripTime": "NA",
                    "bytesReceived": "7484"
                },
                "7c41d8fd": {
                    "id": "7c41d8fd",
                    "timestamp": "1624453051926",
                    "localCandidateId": "6473c45f",
                    "remoteCandidateId": "c51191fe",
                    "state": "inprogress",
                    "priority": "7241259335668204000",
                    "nominated": "false",
                    "bytesSent": "0",
                    "currentRoundTripTime": "NA",
                    "totalRoundTripTime": "NA",
                    "bytesReceived": "0"
                }
            },
            "inbound-rtp": {
                "ad295e29": {
                    "id": "ad295e29",
                    "timestamp": "1624453051926",
                    "ssrc": "3764986905",
                    "kind": "audio",
                    "transportId": "NA",
                    "codecId": "NA",
                    "packetsReceived": "331",
                    "packetsLost": "0",
                    "packetsDiscarded": "NA",
                    "jitter": "0.002",
                    "bytesReceived": "60071",
                    "receiverId": "NA",
                    "remoteId": "79d9e6e1",
                    "nackCount": "0",
                    "audioLevel": "NA",
                    "framesDecoded": "NA",
                    "framesReceived": "NA",
                    "framesDropped": "NA",
                    "partialFramesLost": "NA",
                    "totalAudioEnergy": "NA",
                    "totalSamplesDuration": "NA"
                },
                "3b21103f": {
                    "id": "3b21103f",
                    "timestamp": "1624453051926",
                    "ssrc": "1010522682",
                    "kind": "video",
                    "transportId": "NA",
                    "codecId": "NA",
                    "packetsReceived": "1259",
                    "packetsLost": "0",
                    "packetsDiscarded": "NA",
                    "jitter": "0.015",
                    "bytesReceived": "1374882",
                    "receiverId": "NA",
                    "remoteId": "1d615bea",
                    "nackCount": "0",
                    "audioLevel": "NA",
                    "framesDecoded": "146",
                    "framesReceived": "NA",
                    "framesDropped": "NA",
                    "partialFramesLost": "NA",
                    "totalAudioEnergy": "NA",
                    "totalSamplesDuration": "NA"
                }
            },
            "local-candidate": {
                "6473c45f": {
                    "id": "6473c45f",
                    "timestamp": "1624453051926",
                    "address": "192.168.1.12",
                    "port": "64379",
                    "protocol": "udp",
                    "candidateType": "host",
                    "url": "NA"
                },
                "35c1086c": {
                    "id": "35c1086c",
                    "timestamp": "1624453051926",
                    "address": "2.87.64.185",
                    "port": "64379",
                    "protocol": "udp",
                    "candidateType": "srflx",
                    "url": "NA"
                },
                "478d454a": {
                    "id": "478d454a",
                    "timestamp": "1624453051926",
                    "address": "2a02:587:3e07:5100:e950:d005:6847:63d8",
                    "port": "64380",
                    "protocol": "udp",
                    "candidateType": "host",
                    "url": "NA"
                },
                "aaa35c97": {
                    "id": "aaa35c97",
                    "timestamp": "1624453051926",
                    "address": "192.168.1.12",
                    "port": "56470",
                    "protocol": "tcp",
                    "candidateType": "host",
                    "url": "NA"
                },
                "743313ea": {
                    "id": "743313ea",
                    "timestamp": "1624453051926",
                    "address": "2a02:587:3e07:5100:e950:d005:6847:63d8",
                    "port": "52435",
                    "protocol": "tcp",
                    "candidateType": "host",
                    "url": "NA"
                }
            },
            "outbound-rtp": {
                "409f246b": {
                    "id": "409f246b",
                    "timestamp": "1624453051926",
                    "ssrc": "428917593",
                    "kind": "audio",
                    "transportId": "NA",
                    "codecId": "NA",
                    "packetsSent": "330",
                    "bytesSent": "33330",
                    "senderId": "NA",
                    "remoteId": "3dbd734b",
                    "nackCount": "0",
                    "framesEncoded": "NA",
                    "framesSent": "NA",
                    "framesPerSecond": "NA"
                },
                "ef7b79ec": {
                    "id": "ef7b79ec",
                    "timestamp": "1624453051926",
                    "ssrc": "2069049216",
                    "kind": "video",
                    "transportId": "NA",
                    "codecId": "NA",
                    "packetsSent": "1424",
                    "bytesSent": "1581099",
                    "senderId": "NA",
                    "remoteId": "f8f6730d",
                    "nackCount": "0",
                    "framesEncoded": "167",
                    "framesSent": "NA",
                    "framesPerSecond": "NA"
                }
            },
            "remote-candidate": {
                "e619ce5d": {
                    "id": "e619ce5d",
                    "timestamp": "1624453051926",
                    "address": "192.168.1.12",
                    "port": "56644",
                    "protocol": "udp",
                    "candidateType": "host",
                    "url": "NA"
                },
                "156115ba": {
                    "id": "156115ba",
                    "timestamp": "1624453051926",
                    "address": "2a02:587:3e07:5100:e950:d005:6847:63d8",
                    "port": "49459",
                    "protocol": "udp",
                    "candidateType": "host",
                    "url": "NA"
                },
                "c51191fe": {
                    "id": "c51191fe",
                    "timestamp": "1624453051926",
                    "address": "2.87.64.185",
                    "port": "56644",
                    "protocol": "udp",
                    "candidateType": "srflx",
                    "url": "NA"
                }
            }
        },
        {
            "candidate-pair": {
                "ba3532b9": {
                    "id": "ba3532b9",
                    "timestamp": "1624453053972",
                    "localCandidateId": "478d454a",
                    "remoteCandidateId": "156115ba",
                    "state": "succeeded",
                    "priority": "9115005270282359000",
                    "nominated": "true",
                    "bytesSent": "2102684",
                    "currentRoundTripTime": "NA",
                    "totalRoundTripTime": "NA",
                    "bytesReceived": "2104279"
                },
                "6bc58b3a": {
                    "id": "6bc58b3a",
                    "timestamp": "1624453053972",
                    "localCandidateId": "6473c45f",
                    "remoteCandidateId": "e619ce5d",
                    "state": "succeeded",
                    "priority": "9114723795305512000",
                    "nominated": "true",
                    "bytesSent": "12901",
                    "currentRoundTripTime": "NA",
                    "totalRoundTripTime": "NA",
                    "bytesReceived": "7484"
                },
                "7c41d8fd": {
                    "id": "7c41d8fd",
                    "timestamp": "1624453053972",
                    "localCandidateId": "6473c45f",
                    "remoteCandidateId": "c51191fe",
                    "state": "inprogress",
                    "priority": "7241259335668204000",
                    "nominated": "false",
                    "bytesSent": "0",
                    "currentRoundTripTime": "NA",
                    "totalRoundTripTime": "NA",
                    "bytesReceived": "0"
                }
            },
            "inbound-rtp": {
                "ad295e29": {
                    "id": "ad295e29",
                    "timestamp": "1624453053972",
                    "ssrc": "3764986905",
                    "kind": "audio",
                    "transportId": "NA",
                    "codecId": "NA",
                    "packetsReceived": "433",
                    "packetsLost": "0",
                    "packetsDiscarded": "NA",
                    "jitter": "0.002",
                    "bytesReceived": "78495",
                    "receiverId": "NA",
                    "remoteId": "79d9e6e1",
                    "nackCount": "0",
                    "audioLevel": "NA",
                    "framesDecoded": "NA",
                    "framesReceived": "NA",
                    "framesDropped": "NA",
                    "partialFramesLost": "NA",
                    "totalAudioEnergy": "NA",
                    "totalSamplesDuration": "NA"
                },
                "3b21103f": {
                    "id": "3b21103f",
                    "timestamp": "1624453053973",
                    "ssrc": "1010522682",
                    "kind": "video",
                    "transportId": "NA",
                    "codecId": "NA",
                    "packetsReceived": "1807",
                    "packetsLost": "0",
                    "packetsDiscarded": "NA",
                    "jitter": "0.016",
                    "bytesReceived": "1996795",
                    "receiverId": "NA",
                    "remoteId": "1d615bea",
                    "nackCount": "0",
                    "audioLevel": "NA",
                    "framesDecoded": "206",
                    "framesReceived": "NA",
                    "framesDropped": "NA",
                    "partialFramesLost": "NA",
                    "totalAudioEnergy": "NA",
                    "totalSamplesDuration": "NA"
                }
            },
            "local-candidate": {
                "6473c45f": {
                    "id": "6473c45f",
                    "timestamp": "1624453053972",
                    "address": "192.168.1.12",
                    "port": "64379",
                    "protocol": "udp",
                    "candidateType": "host",
                    "url": "NA"
                },
                "35c1086c": {
                    "id": "35c1086c",
                    "timestamp": "1624453053972",
                    "address": "2.87.64.185",
                    "port": "64379",
                    "protocol": "udp",
                    "candidateType": "srflx",
                    "url": "NA"
                },
                "478d454a": {
                    "id": "478d454a",
                    "timestamp": "1624453053972",
                    "address": "2a02:587:3e07:5100:e950:d005:6847:63d8",
                    "port": "64380",
                    "protocol": "udp",
                    "candidateType": "host",
                    "url": "NA"
                },
                "aaa35c97": {
                    "id": "aaa35c97",
                    "timestamp": "1624453053972",
                    "address": "192.168.1.12",
                    "port": "56470",
                    "protocol": "tcp",
                    "candidateType": "host",
                    "url": "NA"
                },
                "743313ea": {
                    "id": "743313ea",
                    "timestamp": "1624453053972",
                    "address": "2a02:587:3e07:5100:e950:d005:6847:63d8",
                    "port": "52435",
                    "protocol": "tcp",
                    "candidateType": "host",
                    "url": "NA"
                }
            },
            "outbound-rtp": {
                "409f246b": {
                    "id": "409f246b",
                    "timestamp": "1624453053972",
                    "ssrc": "428917593",
                    "kind": "audio",
                    "transportId": "NA",
                    "codecId": "NA",
                    "packetsSent": "433",
                    "bytesSent": "43733",
                    "senderId": "NA",
                    "remoteId": "3dbd734b",
                    "nackCount": "0",
                    "framesEncoded": "NA",
                    "framesSent": "NA",
                    "framesPerSecond": "NA"
                },
                "ef7b79ec": {
                    "id": "ef7b79ec",
                    "timestamp": "1624453053972",
                    "ssrc": "2069049216",
                    "kind": "video",
                    "transportId": "NA",
                    "codecId": "NA",
                    "packetsSent": "1837",
                    "bytesSent": "2035970",
                    "senderId": "NA",
                    "remoteId": "f8f6730d",
                    "nackCount": "0",
                    "framesEncoded": "227",
                    "framesSent": "NA",
                    "framesPerSecond": "NA"
                }
            },
            "remote-candidate": {
                "e619ce5d": {
                    "id": "e619ce5d",
                    "timestamp": "1624453053972",
                    "address": "192.168.1.12",
                    "port": "56644",
                    "protocol": "udp",
                    "candidateType": "host",
                    "url": "NA"
                },
                "156115ba": {
                    "id": "156115ba",
                    "timestamp": "1624453053972",
                    "address": "2a02:587:3e07:5100:e950:d005:6847:63d8",
                    "port": "49459",
                    "protocol": "udp",
                    "candidateType": "host",
                    "url": "NA"
                },
                "c51191fe": {
                    "id": "c51191fe",
                    "timestamp": "1624453053972",
                    "address": "2.87.64.185",
                    "port": "56644",
                    "protocol": "udp",
                    "candidateType": "srflx",
                    "url": "NA"
                }
            }
        },
        {
            "candidate-pair": {
                "ba3532b9": {
                    "id": "ba3532b9",
                    "timestamp": "1624453056017",
                    "localCandidateId": "478d454a",
                    "remoteCandidateId": "156115ba",
                    "state": "succeeded",
                    "priority": "9115005270282359000",
                    "nominated": "true",
                    "bytesSent": "2739112",
                    "currentRoundTripTime": "NA",
                    "totalRoundTripTime": "NA",
                    "bytesReceived": "2864172"
                },
                "6bc58b3a": {
                    "id": "6bc58b3a",
                    "timestamp": "1624453056017",
                    "localCandidateId": "6473c45f",
                    "remoteCandidateId": "e619ce5d",
                    "state": "succeeded",
                    "priority": "9114723795305512000",
                    "nominated": "true",
                    "bytesSent": "12901",
                    "currentRoundTripTime": "NA",
                    "totalRoundTripTime": "NA",
                    "bytesReceived": "7484"
                },
                "7c41d8fd": {
                    "id": "7c41d8fd",
                    "timestamp": "1624453056017",
                    "localCandidateId": "6473c45f",
                    "remoteCandidateId": "c51191fe",
                    "state": "inprogress",
                    "priority": "7241259335668204000",
                    "nominated": "false",
                    "bytesSent": "0",
                    "currentRoundTripTime": "NA",
                    "totalRoundTripTime": "NA",
                    "bytesReceived": "0"
                }
            },
            "inbound-rtp": {
                "ad295e29": {
                    "id": "ad295e29",
                    "timestamp": "1624453056017",
                    "ssrc": "3764986905",
                    "kind": "audio",
                    "transportId": "NA",
                    "codecId": "NA",
                    "packetsReceived": "535",
                    "packetsLost": "0",
                    "packetsDiscarded": "NA",
                    "jitter": "0.002",
                    "bytesReceived": "96995",
                    "receiverId": "NA",
                    "remoteId": "79d9e6e1",
                    "nackCount": "0",
                    "audioLevel": "NA",
                    "framesDecoded": "NA",
                    "framesReceived": "NA",
                    "framesDropped": "NA",
                    "partialFramesLost": "NA",
                    "totalAudioEnergy": "NA",
                    "totalSamplesDuration": "NA"
                },
                "3b21103f": {
                    "id": "3b21103f",
                    "timestamp": "1624453056018",
                    "ssrc": "1010522682",
                    "kind": "video",
                    "transportId": "NA",
                    "codecId": "NA",
                    "packetsReceived": "2445",
                    "packetsLost": "0",
                    "packetsDiscarded": "NA",
                    "jitter": "0.018",
                    "bytesReceived": "2727578",
                    "receiverId": "NA",
                    "remoteId": "1d615bea",
                    "nackCount": "0",
                    "audioLevel": "NA",
                    "framesDecoded": "266",
                    "framesReceived": "NA",
                    "framesDropped": "NA",
                    "partialFramesLost": "NA",
                    "totalAudioEnergy": "NA",
                    "totalSamplesDuration": "NA"
                }
            },
            "local-candidate": {
                "6473c45f": {
                    "id": "6473c45f",
                    "timestamp": "1624453056017",
                    "address": "192.168.1.12",
                    "port": "64379",
                    "protocol": "udp",
                    "candidateType": "host",
                    "url": "NA"
                },
                "35c1086c": {
                    "id": "35c1086c",
                    "timestamp": "1624453056017",
                    "address": "2.87.64.185",
                    "port": "64379",
                    "protocol": "udp",
                    "candidateType": "srflx",
                    "url": "NA"
                },
                "478d454a": {
                    "id": "478d454a",
                    "timestamp": "1624453056017",
                    "address": "2a02:587:3e07:5100:e950:d005:6847:63d8",
                    "port": "64380",
                    "protocol": "udp",
                    "candidateType": "host",
                    "url": "NA"
                },
                "aaa35c97": {
                    "id": "aaa35c97",
                    "timestamp": "1624453056017",
                    "address": "192.168.1.12",
                    "port": "56470",
                    "protocol": "tcp",
                    "candidateType": "host",
                    "url": "NA"
                },
                "743313ea": {
                    "id": "743313ea",
                    "timestamp": "1624453056017",
                    "address": "2a02:587:3e07:5100:e950:d005:6847:63d8",
                    "port": "52435",
                    "protocol": "tcp",
                    "candidateType": "host",
                    "url": "NA"
                }
            },
            "outbound-rtp": {
                "409f246b": {
                    "id": "409f246b",
                    "timestamp": "1624453056017",
                    "ssrc": "428917593",
                    "kind": "audio",
                    "transportId": "NA",
                    "codecId": "NA",
                    "packetsSent": "535",
                    "bytesSent": "54044",
                    "senderId": "NA",
                    "remoteId": "3dbd734b",
                    "nackCount": "0",
                    "framesEncoded": "NA",
                    "framesSent": "NA",
                    "framesPerSecond": "NA"
                },
                "ef7b79ec": {
                    "id": "ef7b79ec",
                    "timestamp": "1624453056017",
                    "ssrc": "2069049216",
                    "kind": "video",
                    "transportId": "NA",
                    "codecId": "NA",
                    "packetsSent": "2388",
                    "bytesSent": "2652053",
                    "senderId": "NA",
                    "remoteId": "f8f6730d",
                    "nackCount": "0",
                    "framesEncoded": "287",
                    "framesSent": "NA",
                    "framesPerSecond": "NA"
                }
            },
            "remote-candidate": {
                "e619ce5d": {
                    "id": "e619ce5d",
                    "timestamp": "1624453056017",
                    "address": "192.168.1.12",
                    "port": "56644",
                    "protocol": "udp",
                    "candidateType": "host",
                    "url": "NA"
                },
                "156115ba": {
                    "id": "156115ba",
                    "timestamp": "1624453056017",
                    "address": "2a02:587:3e07:5100:e950:d005:6847:63d8",
                    "port": "49459",
                    "protocol": "udp",
                    "candidateType": "host",
                    "url": "NA"
                },
                "c51191fe": {
                    "id": "c51191fe",
                    "timestamp": "1624453056017",
                    "address": "2.87.64.185",
                    "port": "56644",
                    "protocol": "udp",
                    "candidateType": "srflx",
                    "url": "NA"
                }
            }
        },
        {
            "candidate-pair": {
                "ba3532b9": {
                    "id": "ba3532b9",
                    "timestamp": "1624453058070",
                    "localCandidateId": "478d454a",
                    "remoteCandidateId": "156115ba",
                    "state": "succeeded",
                    "priority": "9115005270282359000",
                    "nominated": "true",
                    "bytesSent": "3222348",
                    "currentRoundTripTime": "NA",
                    "totalRoundTripTime": "NA",
                    "bytesReceived": "3474888"
                },
                "6bc58b3a": {
                    "id": "6bc58b3a",
                    "timestamp": "1624453058070",
                    "localCandidateId": "6473c45f",
                    "remoteCandidateId": "e619ce5d",
                    "state": "succeeded",
                    "priority": "9114723795305512000",
                    "nominated": "true",
                    "bytesSent": "12901",
                    "currentRoundTripTime": "NA",
                    "totalRoundTripTime": "NA",
                    "bytesReceived": "7484"
                },
                "7c41d8fd": {
                    "id": "7c41d8fd",
                    "timestamp": "1624453058070",
                    "localCandidateId": "6473c45f",
                    "remoteCandidateId": "c51191fe",
                    "state": "failed",
                    "priority": "7241259335668204000",
                    "nominated": "false",
                    "bytesSent": "0",
                    "currentRoundTripTime": "NA",
                    "totalRoundTripTime": "NA",
                    "bytesReceived": "0"
                }
            },
            "inbound-rtp": {
                "ad295e29": {
                    "id": "ad295e29",
                    "timestamp": "1624453058071",
                    "ssrc": "3764986905",
                    "kind": "audio",
                    "transportId": "NA",
                    "codecId": "NA",
                    "packetsReceived": "638",
                    "packetsLost": "0",
                    "packetsDiscarded": "NA",
                    "jitter": "0.002",
                    "bytesReceived": "115478",
                    "receiverId": "NA",
                    "remoteId": "79d9e6e1",
                    "nackCount": "0",
                    "audioLevel": "NA",
                    "framesDecoded": "NA",
                    "framesReceived": "NA",
                    "framesDropped": "NA",
                    "partialFramesLost": "NA",
                    "totalAudioEnergy": "NA",
                    "totalSamplesDuration": "NA"
                },
                "3b21103f": {
                    "id": "3b21103f",
                    "timestamp": "1624453058071",
                    "ssrc": "1010522682",
                    "kind": "video",
                    "transportId": "NA",
                    "codecId": "NA",
                    "packetsReceived": "2964",
                    "packetsLost": "0",
                    "packetsDiscarded": "NA",
                    "jitter": "0.012",
                    "bytesReceived": "3310713",
                    "receiverId": "NA",
                    "remoteId": "1d615bea",
                    "nackCount": "0",
                    "audioLevel": "NA",
                    "framesDecoded": "323",
                    "framesReceived": "NA",
                    "framesDropped": "NA",
                    "partialFramesLost": "NA",
                    "totalAudioEnergy": "NA",
                    "totalSamplesDuration": "NA"
                }
            },
            "local-candidate": {
                "6473c45f": {
                    "id": "6473c45f",
                    "timestamp": "1624453058070",
                    "address": "192.168.1.12",
                    "port": "64379",
                    "protocol": "udp",
                    "candidateType": "host",
                    "url": "NA"
                },
                "35c1086c": {
                    "id": "35c1086c",
                    "timestamp": "1624453058070",
                    "address": "2.87.64.185",
                    "port": "64379",
                    "protocol": "udp",
                    "candidateType": "srflx",
                    "url": "NA"
                },
                "478d454a": {
                    "id": "478d454a",
                    "timestamp": "1624453058070",
                    "address": "2a02:587:3e07:5100:e950:d005:6847:63d8",
                    "port": "64380",
                    "protocol": "udp",
                    "candidateType": "host",
                    "url": "NA"
                },
                "aaa35c97": {
                    "id": "aaa35c97",
                    "timestamp": "1624453058070",
                    "address": "192.168.1.12",
                    "port": "56470",
                    "protocol": "tcp",
                    "candidateType": "host",
                    "url": "NA"
                },
                "743313ea": {
                    "id": "743313ea",
                    "timestamp": "1624453058070",
                    "address": "2a02:587:3e07:5100:e950:d005:6847:63d8",
                    "port": "52435",
                    "protocol": "tcp",
                    "candidateType": "host",
                    "url": "NA"
                }
            },
            "outbound-rtp": {
                "409f246b": {
                    "id": "409f246b",
                    "timestamp": "1624453058071",
                    "ssrc": "428917593",
                    "kind": "audio",
                    "transportId": "NA",
                    "codecId": "NA",
                    "packetsSent": "637",
                    "bytesSent": "64417",
                    "senderId": "NA",
                    "remoteId": "3dbd734b",
                    "nackCount": "0",
                    "framesEncoded": "NA",
                    "framesSent": "NA",
                    "framesPerSecond": "NA"
                },
                "ef7b79ec": {
                    "id": "ef7b79ec",
                    "timestamp": "1624453058071",
                    "ssrc": "2069049216",
                    "kind": "video",
                    "transportId": "NA",
                    "codecId": "NA",
                    "packetsSent": "2802",
                    "bytesSent": "3116550",
                    "senderId": "NA",
                    "remoteId": "f8f6730d",
                    "nackCount": "0",
                    "framesEncoded": "345",
                    "framesSent": "NA",
                    "framesPerSecond": "NA"
                }
            },
            "remote-candidate": {
                "e619ce5d": {
                    "id": "e619ce5d",
                    "timestamp": "1624453058070",
                    "address": "192.168.1.12",
                    "port": "56644",
                    "protocol": "udp",
                    "candidateType": "host",
                    "url": "NA"
                },
                "156115ba": {
                    "id": "156115ba",
                    "timestamp": "1624453058070",
                    "address": "2a02:587:3e07:5100:e950:d005:6847:63d8",
                    "port": "49459",
                    "protocol": "udp",
                    "candidateType": "host",
                    "url": "NA"
                },
                "c51191fe": {
                    "id": "c51191fe",
                    "timestamp": "1624453058070",
                    "address": "2.87.64.185",
                    "port": "56644",
                    "protocol": "udp",
                    "candidateType": "srflx",
                    "url": "NA"
                }
            }
        },
        {
            "candidate-pair": {
                "ba3532b9": {
                    "id": "ba3532b9",
                    "timestamp": "1624453060118",
                    "localCandidateId": "478d454a",
                    "remoteCandidateId": "156115ba",
                    "state": "succeeded",
                    "priority": "9115005270282359000",
                    "nominated": "true",
                    "bytesSent": "3635219",
                    "currentRoundTripTime": "NA",
                    "totalRoundTripTime": "NA",
                    "bytesReceived": "3999150"
                },
                "6bc58b3a": {
                    "id": "6bc58b3a",
                    "timestamp": "1624453060118",
                    "localCandidateId": "6473c45f",
                    "remoteCandidateId": "e619ce5d",
                    "state": "succeeded",
                    "priority": "9114723795305512000",
                    "nominated": "true",
                    "bytesSent": "12901",
                    "currentRoundTripTime": "NA",
                    "totalRoundTripTime": "NA",
                    "bytesReceived": "7484"
                },
                "7c41d8fd": {
                    "id": "7c41d8fd",
                    "timestamp": "1624453060118",
                    "localCandidateId": "6473c45f",
                    "remoteCandidateId": "c51191fe",
                    "state": "failed",
                    "priority": "7241259335668204000",
                    "nominated": "false",
                    "bytesSent": "0",
                    "currentRoundTripTime": "NA",
                    "totalRoundTripTime": "NA",
                    "bytesReceived": "0"
                }
            },
            "inbound-rtp": {
                "ad295e29": {
                    "id": "ad295e29",
                    "timestamp": "1624453060118",
                    "ssrc": "3764986905",
                    "kind": "audio",
                    "transportId": "NA",
                    "codecId": "NA",
                    "packetsReceived": "740",
                    "packetsLost": "0",
                    "packetsDiscarded": "NA",
                    "jitter": "0.002",
                    "bytesReceived": "133940",
                    "receiverId": "NA",
                    "remoteId": "79d9e6e1",
                    "nackCount": "0",
                    "audioLevel": "NA",
                    "framesDecoded": "NA",
                    "framesReceived": "NA",
                    "framesDropped": "NA",
                    "partialFramesLost": "NA",
                    "totalAudioEnergy": "NA",
                    "totalSamplesDuration": "NA"
                },
                "3b21103f": {
                    "id": "3b21103f",
                    "timestamp": "1624453060118",
                    "ssrc": "1010522682",
                    "kind": "video",
                    "transportId": "NA",
                    "codecId": "NA",
                    "packetsReceived": "3414",
                    "packetsLost": "0",
                    "packetsDiscarded": "NA",
                    "jitter": "0.007",
                    "bytesReceived": "3808241",
                    "receiverId": "NA",
                    "remoteId": "1d615bea",
                    "nackCount": "0",
                    "audioLevel": "NA",
                    "framesDecoded": "384",
                    "framesReceived": "NA",
                    "framesDropped": "NA",
                    "partialFramesLost": "NA",
                    "totalAudioEnergy": "NA",
                    "totalSamplesDuration": "NA"
                }
            },
            "local-candidate": {
                "6473c45f": {
                    "id": "6473c45f",
                    "timestamp": "1624453060118",
                    "address": "192.168.1.12",
                    "port": "64379",
                    "protocol": "udp",
                    "candidateType": "host",
                    "url": "NA"
                },
                "35c1086c": {
                    "id": "35c1086c",
                    "timestamp": "1624453060118",
                    "address": "2.87.64.185",
                    "port": "64379",
                    "protocol": "udp",
                    "candidateType": "srflx",
                    "url": "NA"
                },
                "478d454a": {
                    "id": "478d454a",
                    "timestamp": "1624453060118",
                    "address": "2a02:587:3e07:5100:e950:d005:6847:63d8",
                    "port": "64380",
                    "protocol": "udp",
                    "candidateType": "host",
                    "url": "NA"
                },
                "aaa35c97": {
                    "id": "aaa35c97",
                    "timestamp": "1624453060118",
                    "address": "192.168.1.12",
                    "port": "56470",
                    "protocol": "tcp",
                    "candidateType": "host",
                    "url": "NA"
                },
                "743313ea": {
                    "id": "743313ea",
                    "timestamp": "1624453060118",
                    "address": "2a02:587:3e07:5100:e950:d005:6847:63d8",
                    "port": "52435",
                    "protocol": "tcp",
                    "candidateType": "host",
                    "url": "NA"
                }
            },
            "outbound-rtp": {
                "409f246b": {
                    "id": "409f246b",
                    "timestamp": "1624453060118",
                    "ssrc": "428917593",
                    "kind": "audio",
                    "transportId": "NA",
                    "codecId": "NA",
                    "packetsSent": "740",
                    "bytesSent": "74820",
                    "senderId": "NA",
                    "remoteId": "3dbd734b",
                    "nackCount": "0",
                    "framesEncoded": "NA",
                    "framesSent": "NA",
                    "framesPerSecond": "NA"
                },
                "ef7b79ec": {
                    "id": "ef7b79ec",
                    "timestamp": "1624453060118",
                    "ssrc": "2069049216",
                    "kind": "video",
                    "transportId": "NA",
                    "codecId": "NA",
                    "packetsSent": "3168",
                    "bytesSent": "3511830",
                    "senderId": "NA",
                    "remoteId": "f8f6730d",
                    "nackCount": "0",
                    "framesEncoded": "397",
                    "framesSent": "NA",
                    "framesPerSecond": "NA"
                }
            },
            "remote-candidate": {
                "e619ce5d": {
                    "id": "e619ce5d",
                    "timestamp": "1624453060118",
                    "address": "192.168.1.12",
                    "port": "56644",
                    "protocol": "udp",
                    "candidateType": "host",
                    "url": "NA"
                },
                "156115ba": {
                    "id": "156115ba",
                    "timestamp": "1624453060118",
                    "address": "2a02:587:3e07:5100:e950:d005:6847:63d8",
                    "port": "49459",
                    "protocol": "udp",
                    "candidateType": "host",
                    "url": "NA"
                },
                "c51191fe": {
                    "id": "c51191fe",
                    "timestamp": "1624453060118",
                    "address": "2.87.64.185",
                    "port": "56644",
                    "protocol": "udp",
                    "candidateType": "srflx",
                    "url": "NA"
                }
            }
        },
        {
            "candidate-pair": {
                "ba3532b9": {
                    "id": "ba3532b9",
                    "timestamp": "1624453062155",
                    "localCandidateId": "478d454a",
                    "remoteCandidateId": "156115ba",
                    "state": "succeeded",
                    "priority": "9115005270282359000",
                    "nominated": "true",
                    "bytesSent": "4187961",
                    "currentRoundTripTime": "NA",
                    "totalRoundTripTime": "NA",
                    "bytesReceived": "4680583"
                },
                "6bc58b3a": {
                    "id": "6bc58b3a",
                    "timestamp": "1624453062155",
                    "localCandidateId": "6473c45f",
                    "remoteCandidateId": "e619ce5d",
                    "state": "succeeded",
                    "priority": "9114723795305512000",
                    "nominated": "true",
                    "bytesSent": "12901",
                    "currentRoundTripTime": "NA",
                    "totalRoundTripTime": "NA",
                    "bytesReceived": "7484"
                },
                "7c41d8fd": {
                    "id": "7c41d8fd",
                    "timestamp": "1624453062155",
                    "localCandidateId": "6473c45f",
                    "remoteCandidateId": "c51191fe",
                    "state": "failed",
                    "priority": "7241259335668204000",
                    "nominated": "false",
                    "bytesSent": "0",
                    "currentRoundTripTime": "NA",
                    "totalRoundTripTime": "NA",
                    "bytesReceived": "0"
                }
            },
            "inbound-rtp": {
                "ad295e29": {
                    "id": "ad295e29",
                    "timestamp": "1624453062155",
                    "ssrc": "3764986905",
                    "kind": "audio",
                    "transportId": "NA",
                    "codecId": "NA",
                    "packetsReceived": "842",
                    "packetsLost": "0",
                    "packetsDiscarded": "NA",
                    "jitter": "0.002",
                    "bytesReceived": "152402",
                    "receiverId": "NA",
                    "remoteId": "79d9e6e1",
                    "nackCount": "0",
                    "audioLevel": "NA",
                    "framesDecoded": "NA",
                    "framesReceived": "NA",
                    "framesDropped": "NA",
                    "partialFramesLost": "NA",
                    "totalAudioEnergy": "NA",
                    "totalSamplesDuration": "NA"
                },
                "3b21103f": {
                    "id": "3b21103f",
                    "timestamp": "1624453062155",
                    "ssrc": "1010522682",
                    "kind": "video",
                    "transportId": "NA",
                    "codecId": "NA",
                    "packetsReceived": "3992",
                    "packetsLost": "0",
                    "packetsDiscarded": "NA",
                    "jitter": "0.013",
                    "bytesReceived": "4461336",
                    "receiverId": "NA",
                    "remoteId": "1d615bea",
                    "nackCount": "0",
                    "audioLevel": "NA",
                    "framesDecoded": "473",
                    "framesReceived": "NA",
                    "framesDropped": "NA",
                    "partialFramesLost": "NA",
                    "totalAudioEnergy": "NA",
                    "totalSamplesDuration": "NA"
                }
            },
            "local-candidate": {
                "6473c45f": {
                    "id": "6473c45f",
                    "timestamp": "1624453062155",
                    "address": "192.168.1.12",
                    "port": "64379",
                    "protocol": "udp",
                    "candidateType": "host",
                    "url": "NA"
                },
                "35c1086c": {
                    "id": "35c1086c",
                    "timestamp": "1624453062155",
                    "address": "2.87.64.185",
                    "port": "64379",
                    "protocol": "udp",
                    "candidateType": "srflx",
                    "url": "NA"
                },
                "478d454a": {
                    "id": "478d454a",
                    "timestamp": "1624453062155",
                    "address": "2a02:587:3e07:5100:e950:d005:6847:63d8",
                    "port": "64380",
                    "protocol": "udp",
                    "candidateType": "host",
                    "url": "NA"
                },
                "aaa35c97": {
                    "id": "aaa35c97",
                    "timestamp": "1624453062155",
                    "address": "192.168.1.12",
                    "port": "56470",
                    "protocol": "tcp",
                    "candidateType": "host",
                    "url": "NA"
                },
                "743313ea": {
                    "id": "743313ea",
                    "timestamp": "1624453062155",
                    "address": "2a02:587:3e07:5100:e950:d005:6847:63d8",
                    "port": "52435",
                    "protocol": "tcp",
                    "candidateType": "host",
                    "url": "NA"
                }
            },
            "outbound-rtp": {
                "409f246b": {
                    "id": "409f246b",
                    "timestamp": "1624453062155",
                    "ssrc": "428917593",
                    "kind": "audio",
                    "transportId": "NA",
                    "codecId": "NA",
                    "packetsSent": "842",
                    "bytesSent": "85122",
                    "senderId": "NA",
                    "remoteId": "3dbd734b",
                    "nackCount": "0",
                    "framesEncoded": "NA",
                    "framesSent": "NA",
                    "framesPerSecond": "NA"
                },
                "ef7b79ec": {
                    "id": "ef7b79ec",
                    "timestamp": "1624453062155",
                    "ssrc": "2069049216",
                    "kind": "video",
                    "transportId": "NA",
                    "codecId": "NA",
                    "packetsSent": "3644",
                    "bytesSent": "4045238",
                    "senderId": "NA",
                    "remoteId": "f8f6730d",
                    "nackCount": "0",
                    "framesEncoded": "487",
                    "framesSent": "NA",
                    "framesPerSecond": "NA"
                }
            },
            "remote-candidate": {
                "e619ce5d": {
                    "id": "e619ce5d",
                    "timestamp": "1624453062155",
                    "address": "192.168.1.12",
                    "port": "56644",
                    "protocol": "udp",
                    "candidateType": "host",
                    "url": "NA"
                },
                "156115ba": {
                    "id": "156115ba",
                    "timestamp": "1624453062155",
                    "address": "2a02:587:3e07:5100:e950:d005:6847:63d8",
                    "port": "49459",
                    "protocol": "udp",
                    "candidateType": "host",
                    "url": "NA"
                },
                "c51191fe": {
                    "id": "c51191fe",
                    "timestamp": "1624453062155",
                    "address": "2.87.64.185",
                    "port": "56644",
                    "protocol": "udp",
                    "candidateType": "srflx",
                    "url": "NA"
                }
            }
        },
        {
            "candidate-pair": {
                "ba3532b9": {
                    "id": "ba3532b9",
                    "timestamp": "1624453064202",
                    "localCandidateId": "478d454a",
                    "remoteCandidateId": "156115ba",
                    "state": "succeeded",
                    "priority": "9115005270282359000",
                    "nominated": "true",
                    "bytesSent": "4709151",
                    "currentRoundTripTime": "NA",
                    "totalRoundTripTime": "NA",
                    "bytesReceived": "5322884"
                },
                "6bc58b3a": {
                    "id": "6bc58b3a",
                    "timestamp": "1624453064202",
                    "localCandidateId": "6473c45f",
                    "remoteCandidateId": "e619ce5d",
                    "state": "succeeded",
                    "priority": "9114723795305512000",
                    "nominated": "true",
                    "bytesSent": "12901",
                    "currentRoundTripTime": "NA",
                    "totalRoundTripTime": "NA",
                    "bytesReceived": "7484"
                },
                "7c41d8fd": {
                    "id": "7c41d8fd",
                    "timestamp": "1624453064202",
                    "localCandidateId": "6473c45f",
                    "remoteCandidateId": "c51191fe",
                    "state": "failed",
                    "priority": "7241259335668204000",
                    "nominated": "false",
                    "bytesSent": "0",
                    "currentRoundTripTime": "NA",
                    "totalRoundTripTime": "NA",
                    "bytesReceived": "0"
                }
            },
            "inbound-rtp": {
                "ad295e29": {
                    "id": "ad295e29",
                    "timestamp": "1624453064204",
                    "ssrc": "3764986905",
                    "kind": "audio",
                    "transportId": "NA",
                    "codecId": "NA",
                    "packetsReceived": "945",
                    "packetsLost": "0",
                    "packetsDiscarded": "NA",
                    "jitter": "0.002",
                    "bytesReceived": "171045",
                    "receiverId": "NA",
                    "remoteId": "79d9e6e1",
                    "nackCount": "0",
                    "audioLevel": "NA",
                    "framesDecoded": "NA",
                    "framesReceived": "NA",
                    "framesDropped": "NA",
                    "partialFramesLost": "NA",
                    "totalAudioEnergy": "NA",
                    "totalSamplesDuration": "NA"
                },
                "3b21103f": {
                    "id": "3b21103f",
                    "timestamp": "1624453064204",
                    "ssrc": "1010522682",
                    "kind": "video",
                    "transportId": "NA",
                    "codecId": "NA",
                    "packetsReceived": "4534",
                    "packetsLost": "0",
                    "packetsDiscarded": "NA",
                    "jitter": "0.012",
                    "bytesReceived": "5075354",
                    "receiverId": "NA",
                    "remoteId": "1d615bea",
                    "nackCount": "0",
                    "audioLevel": "NA",
                    "framesDecoded": "534",
                    "framesReceived": "NA",
                    "framesDropped": "NA",
                    "partialFramesLost": "NA",
                    "totalAudioEnergy": "NA",
                    "totalSamplesDuration": "NA"
                }
            },
            "local-candidate": {
                "6473c45f": {
                    "id": "6473c45f",
                    "timestamp": "1624453064202",
                    "address": "192.168.1.12",
                    "port": "64379",
                    "protocol": "udp",
                    "candidateType": "host",
                    "url": "NA"
                },
                "35c1086c": {
                    "id": "35c1086c",
                    "timestamp": "1624453064202",
                    "address": "2.87.64.185",
                    "port": "64379",
                    "protocol": "udp",
                    "candidateType": "srflx",
                    "url": "NA"
                },
                "478d454a": {
                    "id": "478d454a",
                    "timestamp": "1624453064202",
                    "address": "2a02:587:3e07:5100:e950:d005:6847:63d8",
                    "port": "64380",
                    "protocol": "udp",
                    "candidateType": "host",
                    "url": "NA"
                },
                "aaa35c97": {
                    "id": "aaa35c97",
                    "timestamp": "1624453064202",
                    "address": "192.168.1.12",
                    "port": "56470",
                    "protocol": "tcp",
                    "candidateType": "host",
                    "url": "NA"
                },
                "743313ea": {
                    "id": "743313ea",
                    "timestamp": "1624453064202",
                    "address": "2a02:587:3e07:5100:e950:d005:6847:63d8",
                    "port": "52435",
                    "protocol": "tcp",
                    "candidateType": "host",
                    "url": "NA"
                }
            },
            "outbound-rtp": {
                "409f246b": {
                    "id": "409f246b",
                    "timestamp": "1624453064203",
                    "ssrc": "428917593",
                    "kind": "audio",
                    "transportId": "NA",
                    "codecId": "NA",
                    "packetsSent": "944",
                    "bytesSent": "95424",
                    "senderId": "NA",
                    "remoteId": "3dbd734b",
                    "nackCount": "0",
                    "framesEncoded": "NA",
                    "framesSent": "NA",
                    "framesPerSecond": "NA"
                },
                "ef7b79ec": {
                    "id": "ef7b79ec",
                    "timestamp": "1624453064204",
                    "ssrc": "2069049216",
                    "kind": "video",
                    "transportId": "NA",
                    "codecId": "NA",
                    "packetsSent": "4090",
                    "bytesSent": "4547394",
                    "senderId": "NA",
                    "remoteId": "f8f6730d",
                    "nackCount": "0",
                    "framesEncoded": "547",
                    "framesSent": "NA",
                    "framesPerSecond": "NA"
                }
            },
            "remote-candidate": {
                "e619ce5d": {
                    "id": "e619ce5d",
                    "timestamp": "1624453064202",
                    "address": "192.168.1.12",
                    "port": "56644",
                    "protocol": "udp",
                    "candidateType": "host",
                    "url": "NA"
                },
                "156115ba": {
                    "id": "156115ba",
                    "timestamp": "1624453064202",
                    "address": "2a02:587:3e07:5100:e950:d005:6847:63d8",
                    "port": "49459",
                    "protocol": "udp",
                    "candidateType": "host",
                    "url": "NA"
                },
                "c51191fe": {
                    "id": "c51191fe",
                    "timestamp": "1624453064202",
                    "address": "2.87.64.185",
                    "port": "56644",
                    "protocol": "udp",
                    "candidateType": "srflx",
                    "url": "NA"
                }
            }
        },
        {
            "candidate-pair": {
                "ba3532b9": {
                    "id": "ba3532b9",
                    "timestamp": "1624453066247",
                    "localCandidateId": "478d454a",
                    "remoteCandidateId": "156115ba",
                    "state": "succeeded",
                    "priority": "9115005270282359000",
                    "nominated": "true",
                    "bytesSent": "5268107",
                    "currentRoundTripTime": "NA",
                    "totalRoundTripTime": "NA",
                    "bytesReceived": "6006983"
                },
                "6bc58b3a": {
                    "id": "6bc58b3a",
                    "timestamp": "1624453066247",
                    "localCandidateId": "6473c45f",
                    "remoteCandidateId": "e619ce5d",
                    "state": "succeeded",
                    "priority": "9114723795305512000",
                    "nominated": "true",
                    "bytesSent": "12901",
                    "currentRoundTripTime": "NA",
                    "totalRoundTripTime": "NA",
                    "bytesReceived": "7484"
                },
                "7c41d8fd": {
                    "id": "7c41d8fd",
                    "timestamp": "1624453066247",
                    "localCandidateId": "6473c45f",
                    "remoteCandidateId": "c51191fe",
                    "state": "failed",
                    "priority": "7241259335668204000",
                    "nominated": "false",
                    "bytesSent": "0",
                    "currentRoundTripTime": "NA",
                    "totalRoundTripTime": "NA",
                    "bytesReceived": "0"
                }
            },
            "inbound-rtp": {
                "ad295e29": {
                    "id": "ad295e29",
                    "timestamp": "1624453066248",
                    "ssrc": "3764986905",
                    "kind": "audio",
                    "transportId": "NA",
                    "codecId": "NA",
                    "packetsReceived": "1047",
                    "packetsLost": "0",
                    "packetsDiscarded": "NA",
                    "jitter": "0.002",
                    "bytesReceived": "189507",
                    "receiverId": "NA",
                    "remoteId": "79d9e6e1",
                    "nackCount": "0",
                    "audioLevel": "NA",
                    "framesDecoded": "NA",
                    "framesReceived": "NA",
                    "framesDropped": "NA",
                    "partialFramesLost": "NA",
                    "totalAudioEnergy": "NA",
                    "totalSamplesDuration": "NA"
                },
                "3b21103f": {
                    "id": "3b21103f",
                    "timestamp": "1624453066248",
                    "ssrc": "1010522682",
                    "kind": "video",
                    "transportId": "NA",
                    "codecId": "NA",
                    "packetsReceived": "5114",
                    "packetsLost": "0",
                    "packetsDiscarded": "NA",
                    "jitter": "0.014",
                    "bytesReceived": "5731181",
                    "receiverId": "NA",
                    "remoteId": "1d615bea",
                    "nackCount": "0",
                    "audioLevel": "NA",
                    "framesDecoded": "593",
                    "framesReceived": "NA",
                    "framesDropped": "NA",
                    "partialFramesLost": "NA",
                    "totalAudioEnergy": "NA",
                    "totalSamplesDuration": "NA"
                }
            },
            "local-candidate": {
                "6473c45f": {
                    "id": "6473c45f",
                    "timestamp": "1624453066247",
                    "address": "192.168.1.12",
                    "port": "64379",
                    "protocol": "udp",
                    "candidateType": "host",
                    "url": "NA"
                },
                "35c1086c": {
                    "id": "35c1086c",
                    "timestamp": "1624453066247",
                    "address": "2.87.64.185",
                    "port": "64379",
                    "protocol": "udp",
                    "candidateType": "srflx",
                    "url": "NA"
                },
                "478d454a": {
                    "id": "478d454a",
                    "timestamp": "1624453066247",
                    "address": "2a02:587:3e07:5100:e950:d005:6847:63d8",
                    "port": "64380",
                    "protocol": "udp",
                    "candidateType": "host",
                    "url": "NA"
                },
                "aaa35c97": {
                    "id": "aaa35c97",
                    "timestamp": "1624453066247",
                    "address": "192.168.1.12",
                    "port": "56470",
                    "protocol": "tcp",
                    "candidateType": "host",
                    "url": "NA"
                },
                "743313ea": {
                    "id": "743313ea",
                    "timestamp": "1624453066247",
                    "address": "2a02:587:3e07:5100:e950:d005:6847:63d8",
                    "port": "52435",
                    "protocol": "tcp",
                    "candidateType": "host",
                    "url": "NA"
                }
            },
            "outbound-rtp": {
                "409f246b": {
                    "id": "409f246b",
                    "timestamp": "1624453066248",
                    "ssrc": "428917593",
                    "kind": "audio",
                    "transportId": "NA",
                    "codecId": "NA",
                    "packetsSent": "1046",
                    "bytesSent": "105722",
                    "senderId": "NA",
                    "remoteId": "3dbd734b",
                    "nackCount": "0",
                    "framesEncoded": "NA",
                    "framesSent": "NA",
                    "framesPerSecond": "NA"
                },
                "ef7b79ec": {
                    "id": "ef7b79ec",
                    "timestamp": "1624453066248",
                    "ssrc": "2069049216",
                    "kind": "video",
                    "transportId": "NA",
                    "codecId": "NA",
                    "packetsSent": "4570",
                    "bytesSent": "5087024",
                    "senderId": "NA",
                    "remoteId": "f8f6730d",
                    "nackCount": "0",
                    "framesEncoded": "607",
                    "framesSent": "NA",
                    "framesPerSecond": "NA"
                }
            },
            "remote-candidate": {
                "e619ce5d": {
                    "id": "e619ce5d",
                    "timestamp": "1624453066247",
                    "address": "192.168.1.12",
                    "port": "56644",
                    "protocol": "udp",
                    "candidateType": "host",
                    "url": "NA"
                },
                "156115ba": {
                    "id": "156115ba",
                    "timestamp": "1624453066247",
                    "address": "2a02:587:3e07:5100:e950:d005:6847:63d8",
                    "port": "49459",
                    "protocol": "udp",
                    "candidateType": "host",
                    "url": "NA"
                },
                "c51191fe": {
                    "id": "c51191fe",
                    "timestamp": "1624453066247",
                    "address": "2.87.64.185",
                    "port": "56644",
                    "protocol": "udp",
                    "candidateType": "srflx",
                    "url": "NA"
                }
            }
        },
        {
            "candidate-pair": {
                "ba3532b9": {
                    "id": "ba3532b9",
                    "timestamp": "1624453068292",
                    "localCandidateId": "478d454a",
                    "remoteCandidateId": "156115ba",
                    "state": "succeeded",
                    "priority": "9115005270282359000",
                    "nominated": "true",
                    "bytesSent": "5866617",
                    "currentRoundTripTime": "NA",
                    "totalRoundTripTime": "NA",
                    "bytesReceived": "6731647"
                },
                "6bc58b3a": {
                    "id": "6bc58b3a",
                    "timestamp": "1624453068292",
                    "localCandidateId": "6473c45f",
                    "remoteCandidateId": "e619ce5d",
                    "state": "succeeded",
                    "priority": "9114723795305512000",
                    "nominated": "true",
                    "bytesSent": "12901",
                    "currentRoundTripTime": "NA",
                    "totalRoundTripTime": "NA",
                    "bytesReceived": "7484"
                },
                "7c41d8fd": {
                    "id": "7c41d8fd",
                    "timestamp": "1624453068292",
                    "localCandidateId": "6473c45f",
                    "remoteCandidateId": "c51191fe",
                    "state": "failed",
                    "priority": "7241259335668204000",
                    "nominated": "false",
                    "bytesSent": "0",
                    "currentRoundTripTime": "NA",
                    "totalRoundTripTime": "NA",
                    "bytesReceived": "0"
                }
            },
            "inbound-rtp": {
                "ad295e29": {
                    "id": "ad295e29",
                    "timestamp": "1624453068293",
                    "ssrc": "3764986905",
                    "kind": "audio",
                    "transportId": "NA",
                    "codecId": "NA",
                    "packetsReceived": "1149",
                    "packetsLost": "0",
                    "packetsDiscarded": "NA",
                    "jitter": "0.002",
                    "bytesReceived": "208129",
                    "receiverId": "NA",
                    "remoteId": "79d9e6e1",
                    "nackCount": "0",
                    "audioLevel": "NA",
                    "framesDecoded": "NA",
                    "framesReceived": "NA",
                    "framesDropped": "NA",
                    "partialFramesLost": "NA",
                    "totalAudioEnergy": "NA",
                    "totalSamplesDuration": "NA"
                },
                "3b21103f": {
                    "id": "3b21103f",
                    "timestamp": "1624453068293",
                    "ssrc": "1010522682",
                    "kind": "video",
                    "transportId": "NA",
                    "codecId": "NA",
                    "packetsReceived": "5725",
                    "packetsLost": "0",
                    "packetsDiscarded": "NA",
                    "jitter": "0.018",
                    "bytesReceived": "6426889",
                    "receiverId": "NA",
                    "remoteId": "1d615bea",
                    "nackCount": "0",
                    "audioLevel": "NA",
                    "framesDecoded": "653",
                    "framesReceived": "NA",
                    "framesDropped": "NA",
                    "partialFramesLost": "NA",
                    "totalAudioEnergy": "NA",
                    "totalSamplesDuration": "NA"
                }
            },
            "local-candidate": {
                "6473c45f": {
                    "id": "6473c45f",
                    "timestamp": "1624453068292",
                    "address": "192.168.1.12",
                    "port": "64379",
                    "protocol": "udp",
                    "candidateType": "host",
                    "url": "NA"
                },
                "35c1086c": {
                    "id": "35c1086c",
                    "timestamp": "1624453068292",
                    "address": "2.87.64.185",
                    "port": "64379",
                    "protocol": "udp",
                    "candidateType": "srflx",
                    "url": "NA"
                },
                "478d454a": {
                    "id": "478d454a",
                    "timestamp": "1624453068292",
                    "address": "2a02:587:3e07:5100:e950:d005:6847:63d8",
                    "port": "64380",
                    "protocol": "udp",
                    "candidateType": "host",
                    "url": "NA"
                },
                "aaa35c97": {
                    "id": "aaa35c97",
                    "timestamp": "1624453068292",
                    "address": "192.168.1.12",
                    "port": "56470",
                    "protocol": "tcp",
                    "candidateType": "host",
                    "url": "NA"
                },
                "743313ea": {
                    "id": "743313ea",
                    "timestamp": "1624453068292",
                    "address": "2a02:587:3e07:5100:e950:d005:6847:63d8",
                    "port": "52435",
                    "protocol": "tcp",
                    "candidateType": "host",
                    "url": "NA"
                }
            },
            "outbound-rtp": {
                "409f246b": {
                    "id": "409f246b",
                    "timestamp": "1624453068292",
                    "ssrc": "428917593",
                    "kind": "audio",
                    "transportId": "NA",
                    "codecId": "NA",
                    "packetsSent": "1148",
                    "bytesSent": "115948",
                    "senderId": "NA",
                    "remoteId": "3dbd734b",
                    "nackCount": "0",
                    "framesEncoded": "NA",
                    "framesSent": "NA",
                    "framesPerSecond": "NA"
                },
                "ef7b79ec": {
                    "id": "ef7b79ec",
                    "timestamp": "1624453068292",
                    "ssrc": "2069049216",
                    "kind": "video",
                    "transportId": "NA",
                    "codecId": "NA",
                    "packetsSent": "5086",
                    "bytesSent": "5668274",
                    "senderId": "NA",
                    "remoteId": "f8f6730d",
                    "nackCount": "0",
                    "framesEncoded": "667",
                    "framesSent": "NA",
                    "framesPerSecond": "NA"
                }
            },
            "remote-candidate": {
                "e619ce5d": {
                    "id": "e619ce5d",
                    "timestamp": "1624453068292",
                    "address": "192.168.1.12",
                    "port": "56644",
                    "protocol": "udp",
                    "candidateType": "host",
                    "url": "NA"
                },
                "156115ba": {
                    "id": "156115ba",
                    "timestamp": "1624453068292",
                    "address": "2a02:587:3e07:5100:e950:d005:6847:63d8",
                    "port": "49459",
                    "protocol": "udp",
                    "candidateType": "host",
                    "url": "NA"
                },
                "c51191fe": {
                    "id": "c51191fe",
                    "timestamp": "1624453068292",
                    "address": "2.87.64.185",
                    "port": "56644",
                    "protocol": "udp",
                    "candidateType": "srflx",
                    "url": "NA"
                }
            }
        }
    ],
    "Network Profile": "",
    "Region Id": "NC",
    "Itinerary": "0"
}