
{
    "Connected": true,
    "Room": "https://appr.tc/r/6177873059092062342",
    "StatsArray": [
        {
            "candidate-pair": {
                "657fac51": {
                    "id": "657fac51",
                    "timestamp": "1624453845122",
                    "localCandidateId": "343fcaa5",
                    "remoteCandidateId": "1894b84e",
                    "state": "cancelled",
                    "priority": "7962083765675491000",
                    "nominated": "false",
                    "bytesSent": "0",
                    "currentRoundTripTime": "NA",
                    "totalRoundTripTime": "NA",
                    "bytesReceived": "0"
                },
                "70c07caf": {
                    "id": "70c07caf",
                    "timestamp": "1624453845122",
                    "localCandidateId": "97870ef5",
                    "remoteCandidateId": "d8769f3f",
                    "state": "succeeded",
                    "priority": "7961802290698650000",
                    "nominated": "true",
                    "bytesSent": "477314",
                    "currentRoundTripTime": "NA",
                    "totalRoundTripTime": "NA",
                    "bytesReceived": "474260"
                }
            },
            "inbound-rtp": {
                "5d967810": {
                    "id": "5d967810",
                    "timestamp": "1624453845122",
                    "ssrc": "1252115303",
                    "kind": "audio",
                    "transportId": "NA",
                    "codecId": "NA",
                    "packetsReceived": "106",
                    "packetsLost": "0",
                    "packetsDiscarded": "NA",
                    "jitter": "0",
                    "bytesReceived": "19186",
                    "receiverId": "NA",
                    "remoteId": "NA",
                    "nackCount": "0",
                    "audioLevel": "NA",
                    "framesDecoded": "NA",
                    "framesReceived": "NA",
                    "framesDropped": "NA",
                    "partialFramesLost": "NA",
                    "totalAudioEnergy": "NA",
                    "totalSamplesDuration": "NA"
                },
                "3b47280e": {
                    "id": "3b47280e",
                    "timestamp": "1624453845122",
                    "ssrc": "1159037486",
                    "kind": "video",
                    "transportId": "NA",
                    "codecId": "NA",
                    "packetsReceived": "394",
                    "packetsLost": "0",
                    "packetsDiscarded": "NA",
                    "jitter": "0.024",
                    "bytesReceived": "443666",
                    "receiverId": "NA",
                    "remoteId": "7e7749e2",
                    "nackCount": "0",
                    "audioLevel": "NA",
                    "framesDecoded": "52",
                    "framesReceived": "NA",
                    "framesDropped": "NA",
                    "partialFramesLost": "NA",
                    "totalAudioEnergy": "NA",
                    "totalSamplesDuration": "NA"
                }
            },
            "local-candidate": {
                "97870ef5": {
                    "id": "97870ef5",
                    "timestamp": "1624453845122",
                    "address": "192.168.1.12",
                    "port": "61357",
                    "protocol": "udp",
                    "candidateType": "host",
                    "url": "NA"
                },
                "f3e3d09c": {
                    "id": "f3e3d09c",
                    "timestamp": "1624453845122",
                    "address": "2.87.64.185",
                    "port": "61357",
                    "protocol": "udp",
                    "candidateType": "srflx",
                    "url": "NA"
                },
                "343fcaa5": {
                    "id": "343fcaa5",
                    "timestamp": "1624453845122",
                    "address": "2a02:587:3e07:5100:e950:d005:6847:63d8",
                    "port": "61358",
                    "protocol": "udp",
                    "candidateType": "host",
                    "url": "NA"
                },
                "62a26437": {
                    "id": "62a26437",
                    "timestamp": "1624453845122",
                    "address": "192.168.1.12",
                    "port": "65434",
                    "protocol": "tcp",
                    "candidateType": "host",
                    "url": "NA"
                },
                "7c433ea6": {
                    "id": "7c433ea6",
                    "timestamp": "1624453845122",
                    "address": "2a02:587:3e07:5100:e950:d005:6847:63d8",
                    "port": "52073",
                    "protocol": "tcp",
                    "candidateType": "host",
                    "url": "NA"
                }
            },
            "outbound-rtp": {
                "e1a31617": {
                    "id": "e1a31617",
                    "timestamp": "1624453845122",
                    "ssrc": "461880480",
                    "kind": "audio",
                    "transportId": "NA",
                    "codecId": "NA",
                    "packetsSent": "106",
                    "bytesSent": "19261",
                    "senderId": "NA",
                    "remoteId": "NA",
                    "nackCount": "0",
                    "framesEncoded": "NA",
                    "framesSent": "NA",
                    "framesPerSecond": "NA"
                },
                "27efc97d": {
                    "id": "27efc97d",
                    "timestamp": "1624453845122",
                    "ssrc": "2329479442",
                    "kind": "video",
                    "transportId": "NA",
                    "codecId": "NA",
                    "packetsSent": "397",
                    "bytesSent": "446622",
                    "senderId": "NA",
                    "remoteId": "2716e83d",
                    "nackCount": "0",
                    "framesEncoded": "49",
                    "framesSent": "NA",
                    "framesPerSecond": "NA"
                }
            },
            "remote-candidate": {
                "d8769f3f": {
                    "id": "d8769f3f",
                    "timestamp": "1624453845122",
                    "address": "192.168.1.12",
                    "port": "57374",
                    "protocol": "udp",
                    "candidateType": "prflx",
                    "url": "NA"
                },
                "1894b84e": {
                    "id": "1894b84e",
                    "timestamp": "1624453845122",
                    "address": "2a02:587:3e07:5100:e950:d005:6847:63d8",
                    "port": "57375",
                    "protocol": "udp",
                    "candidateType": "prflx",
                    "url": "NA"
                }
            }
        },
        {
            "candidate-pair": {
                "657fac51": {
                    "id": "657fac51",
                    "timestamp": "1624453847188",
                    "localCandidateId": "343fcaa5",
                    "remoteCandidateId": "1894b84e",
                    "state": "cancelled",
                    "priority": "7962083765675491000",
                    "nominated": "false",
                    "bytesSent": "0",
                    "currentRoundTripTime": "NA",
                    "totalRoundTripTime": "NA",
                    "bytesReceived": "0"
                },
                "70c07caf": {
                    "id": "70c07caf",
                    "timestamp": "1624453847188",
                    "localCandidateId": "97870ef5",
                    "remoteCandidateId": "d8769f3f",
                    "state": "succeeded",
                    "priority": "7961802290698650000",
                    "nominated": "true",
                    "bytesSent": "1104263",
                    "currentRoundTripTime": "NA",
                    "totalRoundTripTime": "NA",
                    "bytesReceived": "1013135"
                }
            },
            "inbound-rtp": {
                "5d967810": {
                    "id": "5d967810",
                    "timestamp": "1624453847189",
                    "ssrc": "1252115303",
                    "kind": "audio",
                    "transportId": "NA",
                    "codecId": "NA",
                    "packetsReceived": "210",
                    "packetsLost": "0",
                    "packetsDiscarded": "NA",
                    "jitter": "0.004",
                    "bytesReceived": "38010",
                    "receiverId": "NA",
                    "remoteId": "NA",
                    "nackCount": "0",
                    "audioLevel": "NA",
                    "framesDecoded": "NA",
                    "framesReceived": "NA",
                    "framesDropped": "NA",
                    "partialFramesLost": "NA",
                    "totalAudioEnergy": "NA",
                    "totalSamplesDuration": "NA"
                },
                "3b47280e": {
                    "id": "3b47280e",
                    "timestamp": "1624453847189",
                    "ssrc": "1159037486",
                    "kind": "video",
                    "transportId": "NA",
                    "codecId": "NA",
                    "packetsReceived": "846",
                    "packetsLost": "0",
                    "packetsDiscarded": "NA",
                    "jitter": "0.015",
                    "bytesReceived": "951497",
                    "receiverId": "NA",
                    "remoteId": "7e7749e2",
                    "nackCount": "0",
                    "audioLevel": "NA",
                    "framesDecoded": "107",
                    "framesReceived": "NA",
                    "framesDropped": "NA",
                    "partialFramesLost": "NA",
                    "totalAudioEnergy": "NA",
                    "totalSamplesDuration": "NA"
                }
            },
            "local-candidate": {
                "97870ef5": {
                    "id": "97870ef5",
                    "timestamp": "1624453847188",
                    "address": "192.168.1.12",
                    "port": "61357",
                    "protocol": "udp",
                    "candidateType": "host",
                    "url": "NA"
                },
                "f3e3d09c": {
                    "id": "f3e3d09c",
                    "timestamp": "1624453847188",
                    "address": "2.87.64.185",
                    "port": "61357",
                    "protocol": "udp",
                    "candidateType": "srflx",
                    "url": "NA"
                },
                "343fcaa5": {
                    "id": "343fcaa5",
                    "timestamp": "1624453847188",
                    "address": "2a02:587:3e07:5100:e950:d005:6847:63d8",
                    "port": "61358",
                    "protocol": "udp",
                    "candidateType": "host",
                    "url": "NA"
                },
                "62a26437": {
                    "id": "62a26437",
                    "timestamp": "1624453847188",
                    "address": "192.168.1.12",
                    "port": "65434",
                    "protocol": "tcp",
                    "candidateType": "host",
                    "url": "NA"
                },
                "7c433ea6": {
                    "id": "7c433ea6",
                    "timestamp": "1624453847188",
                    "address": "2a02:587:3e07:5100:e950:d005:6847:63d8",
                    "port": "52073",
                    "protocol": "tcp",
                    "candidateType": "host",
                    "url": "NA"
                }
            },
            "outbound-rtp": {
                "e1a31617": {
                    "id": "e1a31617",
                    "timestamp": "1624453847188",
                    "ssrc": "461880480",
                    "kind": "audio",
                    "transportId": "NA",
                    "codecId": "NA",
                    "packetsSent": "210",
                    "bytesSent": "38148",
                    "senderId": "NA",
                    "remoteId": "NA",
                    "nackCount": "0",
                    "framesEncoded": "NA",
                    "framesSent": "NA",
                    "framesPerSecond": "NA"
                },
                "27efc97d": {
                    "id": "27efc97d",
                    "timestamp": "1624453847189",
                    "ssrc": "2329479442",
                    "kind": "video",
                    "transportId": "NA",
                    "codecId": "NA",
                    "packetsSent": "922",
                    "bytesSent": "1041012",
                    "senderId": "NA",
                    "remoteId": "2716e83d",
                    "nackCount": "0",
                    "framesEncoded": "105",
                    "framesSent": "NA",
                    "framesPerSecond": "NA"
                }
            },
            "remote-candidate": {
                "d8769f3f": {
                    "id": "d8769f3f",
                    "timestamp": "1624453847188",
                    "address": "192.168.1.12",
                    "port": "57374",
                    "protocol": "udp",
                    "candidateType": "prflx",
                    "url": "NA"
                },
                "1894b84e": {
                    "id": "1894b84e",
                    "timestamp": "1624453847188",
                    "address": "2a02:587:3e07:5100:e950:d005:6847:63d8",
                    "port": "57375",
                    "protocol": "udp",
                    "candidateType": "prflx",
                    "url": "NA"
                }
            }
        },
        {
            "candidate-pair": {
                "657fac51": {
                    "id": "657fac51",
                    "timestamp": "1624453849268",
                    "localCandidateId": "343fcaa5",
                    "remoteCandidateId": "1894b84e",
                    "state": "cancelled",
                    "priority": "7962083765675491000",
                    "nominated": "false",
                    "bytesSent": "0",
                    "currentRoundTripTime": "NA",
                    "totalRoundTripTime": "NA",
                    "bytesReceived": "0"
                },
                "70c07caf": {
                    "id": "70c07caf",
                    "timestamp": "1624453849268",
                    "localCandidateId": "97870ef5",
                    "remoteCandidateId": "d8769f3f",
                    "state": "succeeded",
                    "priority": "7961802290698650000",
                    "nominated": "true",
                    "bytesSent": "1678371",
                    "currentRoundTripTime": "NA",
                    "totalRoundTripTime": "NA",
                    "bytesReceived": "1594682"
                }
            },
            "inbound-rtp": {
                "5d967810": {
                    "id": "5d967810",
                    "timestamp": "1624453849268",
                    "ssrc": "1252115303",
                    "kind": "audio",
                    "transportId": "NA",
                    "codecId": "NA",
                    "packetsReceived": "313",
                    "packetsLost": "0",
                    "packetsDiscarded": "NA",
                    "jitter": "0.004",
                    "bytesReceived": "56813",
                    "receiverId": "NA",
                    "remoteId": "NA",
                    "nackCount": "0",
                    "audioLevel": "NA",
                    "framesDecoded": "NA",
                    "framesReceived": "NA",
                    "framesDropped": "NA",
                    "partialFramesLost": "NA",
                    "totalAudioEnergy": "NA",
                    "totalSamplesDuration": "NA"
                },
                "3b47280e": {
                    "id": "3b47280e",
                    "timestamp": "1624453849268",
                    "ssrc": "1159037486",
                    "kind": "video",
                    "transportId": "NA",
                    "codecId": "NA",
                    "packetsReceived": "1333",
                    "packetsLost": "0",
                    "packetsDiscarded": "NA",
                    "jitter": "0.009",
                    "bytesReceived": "1501277",
                    "receiverId": "NA",
                    "remoteId": "7e7749e2",
                    "nackCount": "0",
                    "audioLevel": "NA",
                    "framesDecoded": "163",
                    "framesReceived": "NA",
                    "framesDropped": "NA",
                    "partialFramesLost": "NA",
                    "totalAudioEnergy": "NA",
                    "totalSamplesDuration": "NA"
                }
            },
            "local-candidate": {
                "97870ef5": {
                    "id": "97870ef5",
                    "timestamp": "1624453849268",
                    "address": "192.168.1.12",
                    "port": "61357",
                    "protocol": "udp",
                    "candidateType": "host",
                    "url": "NA"
                },
                "f3e3d09c": {
                    "id": "f3e3d09c",
                    "timestamp": "1624453849268",
                    "address": "2.87.64.185",
                    "port": "61357",
                    "protocol": "udp",
                    "candidateType": "srflx",
                    "url": "NA"
                },
                "343fcaa5": {
                    "id": "343fcaa5",
                    "timestamp": "1624453849268",
                    "address": "2a02:587:3e07:5100:e950:d005:6847:63d8",
                    "port": "61358",
                    "protocol": "udp",
                    "candidateType": "host",
                    "url": "NA"
                },
                "62a26437": {
                    "id": "62a26437",
                    "timestamp": "1624453849268",
                    "address": "192.168.1.12",
                    "port": "65434",
                    "protocol": "tcp",
                    "candidateType": "host",
                    "url": "NA"
                },
                "7c433ea6": {
                    "id": "7c433ea6",
                    "timestamp": "1624453849268",
                    "address": "2a02:587:3e07:5100:e950:d005:6847:63d8",
                    "port": "52073",
                    "protocol": "tcp",
                    "candidateType": "host",
                    "url": "NA"
                }
            },
            "outbound-rtp": {
                "e1a31617": {
                    "id": "e1a31617",
                    "timestamp": "1624453849268",
                    "ssrc": "461880480",
                    "kind": "audio",
                    "transportId": "NA",
                    "codecId": "NA",
                    "packetsSent": "313",
                    "bytesSent": "56793",
                    "senderId": "NA",
                    "remoteId": "NA",
                    "nackCount": "0",
                    "framesEncoded": "NA",
                    "framesSent": "NA",
                    "framesPerSecond": "NA"
                },
                "27efc97d": {
                    "id": "27efc97d",
                    "timestamp": "1624453849268",
                    "ssrc": "2329479442",
                    "kind": "video",
                    "transportId": "NA",
                    "codecId": "NA",
                    "packetsSent": "1403",
                    "bytesSent": "1583751",
                    "senderId": "NA",
                    "remoteId": "2716e83d",
                    "nackCount": "0",
                    "framesEncoded": "161",
                    "framesSent": "NA",
                    "framesPerSecond": "NA"
                }
            },
            "remote-candidate": {
                "d8769f3f": {
                    "id": "d8769f3f",
                    "timestamp": "1624453849268",
                    "address": "192.168.1.12",
                    "port": "57374",
                    "protocol": "udp",
                    "candidateType": "prflx",
                    "url": "NA"
                },
                "1894b84e": {
                    "id": "1894b84e",
                    "timestamp": "1624453849268",
                    "address": "2a02:587:3e07:5100:e950:d005:6847:63d8",
                    "port": "57375",
                    "protocol": "udp",
                    "candidateType": "prflx",
                    "url": "NA"
                }
            }
        },
        {
            "candidate-pair": {
                "657fac51": {
                    "id": "657fac51",
                    "timestamp": "1624453851329",
                    "localCandidateId": "343fcaa5",
                    "remoteCandidateId": "1894b84e",
                    "state": "cancelled",
                    "priority": "7962083765675491000",
                    "nominated": "false",
                    "bytesSent": "0",
                    "currentRoundTripTime": "NA",
                    "totalRoundTripTime": "NA",
                    "bytesReceived": "0"
                },
                "70c07caf": {
                    "id": "70c07caf",
                    "timestamp": "1624453851329",
                    "localCandidateId": "97870ef5",
                    "remoteCandidateId": "d8769f3f",
                    "state": "succeeded",
                    "priority": "7961802290698650000",
                    "nominated": "true",
                    "bytesSent": "1997404",
                    "currentRoundTripTime": "NA",
                    "totalRoundTripTime": "NA",
                    "bytesReceived": "1997875"
                }
            },
            "inbound-rtp": {
                "5d967810": {
                    "id": "5d967810",
                    "timestamp": "1624453851331",
                    "ssrc": "1252115303",
                    "kind": "audio",
                    "transportId": "NA",
                    "codecId": "NA",
                    "packetsReceived": "416",
                    "packetsLost": "0",
                    "packetsDiscarded": "NA",
                    "jitter": "0.004",
                    "bytesReceived": "75296",
                    "receiverId": "NA",
                    "remoteId": "c75d25",
                    "nackCount": "0",
                    "audioLevel": "NA",
                    "framesDecoded": "NA",
                    "framesReceived": "NA",
                    "framesDropped": "NA",
                    "partialFramesLost": "NA",
                    "totalAudioEnergy": "NA",
                    "totalSamplesDuration": "NA"
                },
                "3b47280e": {
                    "id": "3b47280e",
                    "timestamp": "1624453851331",
                    "ssrc": "1159037486",
                    "kind": "video",
                    "transportId": "NA",
                    "codecId": "NA",
                    "packetsReceived": "1678",
                    "packetsLost": "0",
                    "packetsDiscarded": "NA",
                    "jitter": "0.009",
                    "bytesReceived": "1875643",
                    "receiverId": "NA",
                    "remoteId": "7e7749e2",
                    "nackCount": "0",
                    "audioLevel": "NA",
                    "framesDecoded": "221",
                    "framesReceived": "NA",
                    "framesDropped": "NA",
                    "partialFramesLost": "NA",
                    "totalAudioEnergy": "NA",
                    "totalSamplesDuration": "NA"
                }
            },
            "local-candidate": {
                "97870ef5": {
                    "id": "97870ef5",
                    "timestamp": "1624453851329",
                    "address": "192.168.1.12",
                    "port": "61357",
                    "protocol": "udp",
                    "candidateType": "host",
                    "url": "NA"
                },
                "f3e3d09c": {
                    "id": "f3e3d09c",
                    "timestamp": "1624453851329",
                    "address": "2.87.64.185",
                    "port": "61357",
                    "protocol": "udp",
                    "candidateType": "srflx",
                    "url": "NA"
                },
                "343fcaa5": {
                    "id": "343fcaa5",
                    "timestamp": "1624453851329",
                    "address": "2a02:587:3e07:5100:e950:d005:6847:63d8",
                    "port": "61358",
                    "protocol": "udp",
                    "candidateType": "host",
                    "url": "NA"
                },
                "62a26437": {
                    "id": "62a26437",
                    "timestamp": "1624453851329",
                    "address": "192.168.1.12",
                    "port": "65434",
                    "protocol": "tcp",
                    "candidateType": "host",
                    "url": "NA"
                },
                "7c433ea6": {
                    "id": "7c433ea6",
                    "timestamp": "1624453851329",
                    "address": "2a02:587:3e07:5100:e950:d005:6847:63d8",
                    "port": "52073",
                    "protocol": "tcp",
                    "candidateType": "host",
                    "url": "NA"
                }
            },
            "outbound-rtp": {
                "e1a31617": {
                    "id": "e1a31617",
                    "timestamp": "1624453851331",
                    "ssrc": "461880480",
                    "kind": "audio",
                    "transportId": "NA",
                    "codecId": "NA",
                    "packetsSent": "416",
                    "bytesSent": "75296",
                    "senderId": "NA",
                    "remoteId": "NA",
                    "nackCount": "0",
                    "framesEncoded": "NA",
                    "framesSent": "NA",
                    "framesPerSecond": "NA"
                },
                "27efc97d": {
                    "id": "27efc97d",
                    "timestamp": "1624453851331",
                    "ssrc": "2329479442",
                    "kind": "video",
                    "transportId": "NA",
                    "codecId": "NA",
                    "packetsSent": "1678",
                    "bytesSent": "1874713",
                    "senderId": "NA",
                    "remoteId": "2716e83d",
                    "nackCount": "0",
                    "framesEncoded": "210",
                    "framesSent": "NA",
                    "framesPerSecond": "NA"
                }
            },
            "remote-candidate": {
                "d8769f3f": {
                    "id": "d8769f3f",
                    "timestamp": "1624453851329",
                    "address": "192.168.1.12",
                    "port": "57374",
                    "protocol": "udp",
                    "candidateType": "prflx",
                    "url": "NA"
                },
                "1894b84e": {
                    "id": "1894b84e",
                    "timestamp": "1624453851329",
                    "address": "2a02:587:3e07:5100:e950:d005:6847:63d8",
                    "port": "57375",
                    "protocol": "udp",
                    "candidateType": "prflx",
                    "url": "NA"
                }
            }
        },
        {
            "candidate-pair": {
                "657fac51": {
                    "id": "657fac51",
                    "timestamp": "1624453853387",
                    "localCandidateId": "343fcaa5",
                    "remoteCandidateId": "1894b84e",
                    "state": "cancelled",
                    "priority": "7962083765675491000",
                    "nominated": "false",
                    "bytesSent": "0",
                    "currentRoundTripTime": "NA",
                    "totalRoundTripTime": "NA",
                    "bytesReceived": "0"
                },
                "70c07caf": {
                    "id": "70c07caf",
                    "timestamp": "1624453853387",
                    "localCandidateId": "97870ef5",
                    "remoteCandidateId": "d8769f3f",
                    "state": "succeeded",
                    "priority": "7961802290698650000",
                    "nominated": "true",
                    "bytesSent": "2652445",
                    "currentRoundTripTime": "NA",
                    "totalRoundTripTime": "NA",
                    "bytesReceived": "2603093"
                }
            },
            "inbound-rtp": {
                "5d967810": {
                    "id": "5d967810",
                    "timestamp": "1624453853388",
                    "ssrc": "1252115303",
                    "kind": "audio",
                    "transportId": "NA",
                    "codecId": "NA",
                    "packetsReceived": "519",
                    "packetsLost": "0",
                    "packetsDiscarded": "NA",
                    "jitter": "0.004",
                    "bytesReceived": "94099",
                    "receiverId": "NA",
                    "remoteId": "c75d25",
                    "nackCount": "0",
                    "audioLevel": "NA",
                    "framesDecoded": "NA",
                    "framesReceived": "NA",
                    "framesDropped": "NA",
                    "partialFramesLost": "NA",
                    "totalAudioEnergy": "NA",
                    "totalSamplesDuration": "NA"
                },
                "3b47280e": {
                    "id": "3b47280e",
                    "timestamp": "1624453853388",
                    "ssrc": "1159037486",
                    "kind": "video",
                    "transportId": "NA",
                    "codecId": "NA",
                    "packetsReceived": "2186",
                    "packetsLost": "0",
                    "packetsDiscarded": "NA",
                    "jitter": "0.011",
                    "bytesReceived": "2448842",
                    "receiverId": "NA",
                    "remoteId": "7e7749e2",
                    "nackCount": "0",
                    "audioLevel": "NA",
                    "framesDecoded": "278",
                    "framesReceived": "NA",
                    "framesDropped": "NA",
                    "partialFramesLost": "NA",
                    "totalAudioEnergy": "NA",
                    "totalSamplesDuration": "NA"
                }
            },
            "local-candidate": {
                "97870ef5": {
                    "id": "97870ef5",
                    "timestamp": "1624453853387",
                    "address": "192.168.1.12",
                    "port": "61357",
                    "protocol": "udp",
                    "candidateType": "host",
                    "url": "NA"
                },
                "f3e3d09c": {
                    "id": "f3e3d09c",
                    "timestamp": "1624453853387",
                    "address": "2.87.64.185",
                    "port": "61357",
                    "protocol": "udp",
                    "candidateType": "srflx",
                    "url": "NA"
                },
                "343fcaa5": {
                    "id": "343fcaa5",
                    "timestamp": "1624453853387",
                    "address": "2a02:587:3e07:5100:e950:d005:6847:63d8",
                    "port": "61358",
                    "protocol": "udp",
                    "candidateType": "host",
                    "url": "NA"
                },
                "62a26437": {
                    "id": "62a26437",
                    "timestamp": "1624453853387",
                    "address": "192.168.1.12",
                    "port": "65434",
                    "protocol": "tcp",
                    "candidateType": "host",
                    "url": "NA"
                },
                "7c433ea6": {
                    "id": "7c433ea6",
                    "timestamp": "1624453853387",
                    "address": "2a02:587:3e07:5100:e950:d005:6847:63d8",
                    "port": "52073",
                    "protocol": "tcp",
                    "candidateType": "host",
                    "url": "NA"
                }
            },
            "outbound-rtp": {
                "e1a31617": {
                    "id": "e1a31617",
                    "timestamp": "1624453853388",
                    "ssrc": "461880480",
                    "kind": "audio",
                    "transportId": "NA",
                    "codecId": "NA",
                    "packetsSent": "520",
                    "bytesSent": "94120",
                    "senderId": "NA",
                    "remoteId": "NA",
                    "nackCount": "0",
                    "framesEncoded": "NA",
                    "framesSent": "NA",
                    "framesPerSecond": "NA"
                },
                "27efc97d": {
                    "id": "27efc97d",
                    "timestamp": "1624453853388",
                    "ssrc": "2329479442",
                    "kind": "video",
                    "transportId": "NA",
                    "codecId": "NA",
                    "packetsSent": "2226",
                    "bytesSent": "2497343",
                    "senderId": "NA",
                    "remoteId": "2716e83d",
                    "nackCount": "0",
                    "framesEncoded": "268",
                    "framesSent": "NA",
                    "framesPerSecond": "NA"
                }
            },
            "remote-candidate": {
                "d8769f3f": {
                    "id": "d8769f3f",
                    "timestamp": "1624453853387",
                    "address": "192.168.1.12",
                    "port": "57374",
                    "protocol": "udp",
                    "candidateType": "prflx",
                    "url": "NA"
                },
                "1894b84e": {
                    "id": "1894b84e",
                    "timestamp": "1624453853387",
                    "address": "2a02:587:3e07:5100:e950:d005:6847:63d8",
                    "port": "57375",
                    "protocol": "udp",
                    "candidateType": "prflx",
                    "url": "NA"
                }
            }
        },
        {
            "candidate-pair": {
                "657fac51": {
                    "id": "657fac51",
                    "timestamp": "1624453855438",
                    "localCandidateId": "343fcaa5",
                    "remoteCandidateId": "1894b84e",
                    "state": "cancelled",
                    "priority": "7962083765675491000",
                    "nominated": "false",
                    "bytesSent": "0",
                    "currentRoundTripTime": "NA",
                    "totalRoundTripTime": "NA",
                    "bytesReceived": "0"
                },
                "70c07caf": {
                    "id": "70c07caf",
                    "timestamp": "1624453855438",
                    "localCandidateId": "97870ef5",
                    "remoteCandidateId": "d8769f3f",
                    "state": "succeeded",
                    "priority": "7961802290698650000",
                    "nominated": "true",
                    "bytesSent": "3213322",
                    "currentRoundTripTime": "NA",
                    "totalRoundTripTime": "NA",
                    "bytesReceived": "3195500"
                }
            },
            "inbound-rtp": {
                "5d967810": {
                    "id": "5d967810",
                    "timestamp": "1624453855439",
                    "ssrc": "1252115303",
                    "kind": "audio",
                    "transportId": "NA",
                    "codecId": "NA",
                    "packetsReceived": "622",
                    "packetsLost": "0",
                    "packetsDiscarded": "NA",
                    "jitter": "0.004",
                    "bytesReceived": "112742",
                    "receiverId": "NA",
                    "remoteId": "c75d25",
                    "nackCount": "0",
                    "audioLevel": "NA",
                    "framesDecoded": "NA",
                    "framesReceived": "NA",
                    "framesDropped": "NA",
                    "partialFramesLost": "NA",
                    "totalAudioEnergy": "NA",
                    "totalSamplesDuration": "NA"
                },
                "3b47280e": {
                    "id": "3b47280e",
                    "timestamp": "1624453855439",
                    "ssrc": "1159037486",
                    "kind": "video",
                    "transportId": "NA",
                    "codecId": "NA",
                    "packetsReceived": "2681",
                    "packetsLost": "0",
                    "packetsDiscarded": "NA",
                    "jitter": "0.012",
                    "bytesReceived": "3009594",
                    "receiverId": "NA",
                    "remoteId": "7e7749e2",
                    "nackCount": "0",
                    "audioLevel": "NA",
                    "framesDecoded": "336",
                    "framesReceived": "NA",
                    "framesDropped": "NA",
                    "partialFramesLost": "NA",
                    "totalAudioEnergy": "NA",
                    "totalSamplesDuration": "NA"
                }
            },
            "local-candidate": {
                "97870ef5": {
                    "id": "97870ef5",
                    "timestamp": "1624453855438",
                    "address": "192.168.1.12",
                    "port": "61357",
                    "protocol": "udp",
                    "candidateType": "host",
                    "url": "NA"
                },
                "f3e3d09c": {
                    "id": "f3e3d09c",
                    "timestamp": "1624453855438",
                    "address": "2.87.64.185",
                    "port": "61357",
                    "protocol": "udp",
                    "candidateType": "srflx",
                    "url": "NA"
                },
                "343fcaa5": {
                    "id": "343fcaa5",
                    "timestamp": "1624453855438",
                    "address": "2a02:587:3e07:5100:e950:d005:6847:63d8",
                    "port": "61358",
                    "protocol": "udp",
                    "candidateType": "host",
                    "url": "NA"
                },
                "62a26437": {
                    "id": "62a26437",
                    "timestamp": "1624453855438",
                    "address": "192.168.1.12",
                    "port": "65434",
                    "protocol": "tcp",
                    "candidateType": "host",
                    "url": "NA"
                },
                "7c433ea6": {
                    "id": "7c433ea6",
                    "timestamp": "1624453855438",
                    "address": "2a02:587:3e07:5100:e950:d005:6847:63d8",
                    "port": "52073",
                    "protocol": "tcp",
                    "candidateType": "host",
                    "url": "NA"
                }
            },
            "outbound-rtp": {
                "e1a31617": {
                    "id": "e1a31617",
                    "timestamp": "1624453855439",
                    "ssrc": "461880480",
                    "kind": "audio",
                    "transportId": "NA",
                    "codecId": "NA",
                    "packetsSent": "622",
                    "bytesSent": "112582",
                    "senderId": "NA",
                    "remoteId": "NA",
                    "nackCount": "0",
                    "framesEncoded": "NA",
                    "framesSent": "NA",
                    "framesPerSecond": "NA"
                },
                "27efc97d": {
                    "id": "27efc97d",
                    "timestamp": "1624453855439",
                    "ssrc": "2329479442",
                    "kind": "video",
                    "transportId": "NA",
                    "codecId": "NA",
                    "packetsSent": "2701",
                    "bytesSent": "3026605",
                    "senderId": "NA",
                    "remoteId": "2716e83d",
                    "nackCount": "0",
                    "framesEncoded": "328",
                    "framesSent": "NA",
                    "framesPerSecond": "NA"
                }
            },
            "remote-candidate": {
                "d8769f3f": {
                    "id": "d8769f3f",
                    "timestamp": "1624453855438",
                    "address": "192.168.1.12",
                    "port": "57374",
                    "protocol": "udp",
                    "candidateType": "prflx",
                    "url": "NA"
                },
                "1894b84e": {
                    "id": "1894b84e",
                    "timestamp": "1624453855438",
                    "address": "2a02:587:3e07:5100:e950:d005:6847:63d8",
                    "port": "57375",
                    "protocol": "udp",
                    "candidateType": "prflx",
                    "url": "NA"
                }
            }
        },
        {
            "candidate-pair": {
                "657fac51": {
                    "id": "657fac51",
                    "timestamp": "1624453857489",
                    "localCandidateId": "343fcaa5",
                    "remoteCandidateId": "1894b84e",
                    "state": "cancelled",
                    "priority": "7962083765675491000",
                    "nominated": "false",
                    "bytesSent": "0",
                    "currentRoundTripTime": "NA",
                    "totalRoundTripTime": "NA",
                    "bytesReceived": "0"
                },
                "70c07caf": {
                    "id": "70c07caf",
                    "timestamp": "1624453857489",
                    "localCandidateId": "97870ef5",
                    "remoteCandidateId": "d8769f3f",
                    "state": "succeeded",
                    "priority": "7961802290698650000",
                    "nominated": "true",
                    "bytesSent": "3698365",
                    "currentRoundTripTime": "NA",
                    "totalRoundTripTime": "NA",
                    "bytesReceived": "3640392"
                }
            },
            "inbound-rtp": {
                "5d967810": {
                    "id": "5d967810",
                    "timestamp": "1624453857492",
                    "ssrc": "1252115303",
                    "kind": "audio",
                    "transportId": "NA",
                    "codecId": "NA",
                    "packetsReceived": "725",
                    "packetsLost": "0",
                    "packetsDiscarded": "NA",
                    "jitter": "0.004",
                    "bytesReceived": "131385",
                    "receiverId": "NA",
                    "remoteId": "c75d25",
                    "nackCount": "0",
                    "audioLevel": "NA",
                    "framesDecoded": "NA",
                    "framesReceived": "NA",
                    "framesDropped": "NA",
                    "partialFramesLost": "NA",
                    "totalAudioEnergy": "NA",
                    "totalSamplesDuration": "NA"
                },
                "3b47280e": {
                    "id": "3b47280e",
                    "timestamp": "1624453857493",
                    "ssrc": "1159037486",
                    "kind": "video",
                    "transportId": "NA",
                    "codecId": "NA",
                    "packetsReceived": "3057",
                    "packetsLost": "0",
                    "packetsDiscarded": "NA",
                    "jitter": "0.012",
                    "bytesReceived": "3425159",
                    "receiverId": "NA",
                    "remoteId": "7e7749e2",
                    "nackCount": "0",
                    "audioLevel": "NA",
                    "framesDecoded": "395",
                    "framesReceived": "NA",
                    "framesDropped": "NA",
                    "partialFramesLost": "NA",
                    "totalAudioEnergy": "NA",
                    "totalSamplesDuration": "NA"
                }
            },
            "local-candidate": {
                "97870ef5": {
                    "id": "97870ef5",
                    "timestamp": "1624453857489",
                    "address": "192.168.1.12",
                    "port": "61357",
                    "protocol": "udp",
                    "candidateType": "host",
                    "url": "NA"
                },
                "f3e3d09c": {
                    "id": "f3e3d09c",
                    "timestamp": "1624453857489",
                    "address": "2.87.64.185",
                    "port": "61357",
                    "protocol": "udp",
                    "candidateType": "srflx",
                    "url": "NA"
                },
                "343fcaa5": {
                    "id": "343fcaa5",
                    "timestamp": "1624453857489",
                    "address": "2a02:587:3e07:5100:e950:d005:6847:63d8",
                    "port": "61358",
                    "protocol": "udp",
                    "candidateType": "host",
                    "url": "NA"
                },
                "62a26437": {
                    "id": "62a26437",
                    "timestamp": "1624453857489",
                    "address": "192.168.1.12",
                    "port": "65434",
                    "protocol": "tcp",
                    "candidateType": "host",
                    "url": "NA"
                },
                "7c433ea6": {
                    "id": "7c433ea6",
                    "timestamp": "1624453857489",
                    "address": "2a02:587:3e07:5100:e950:d005:6847:63d8",
                    "port": "52073",
                    "protocol": "tcp",
                    "candidateType": "host",
                    "url": "NA"
                }
            },
            "outbound-rtp": {
                "e1a31617": {
                    "id": "e1a31617",
                    "timestamp": "1624453857492",
                    "ssrc": "461880480",
                    "kind": "audio",
                    "transportId": "NA",
                    "codecId": "NA",
                    "packetsSent": "724",
                    "bytesSent": "131044",
                    "senderId": "NA",
                    "remoteId": "596474ca",
                    "nackCount": "0",
                    "framesEncoded": "NA",
                    "framesSent": "NA",
                    "framesPerSecond": "NA"
                },
                "27efc97d": {
                    "id": "27efc97d",
                    "timestamp": "1624453857492",
                    "ssrc": "2329479442",
                    "kind": "video",
                    "transportId": "NA",
                    "codecId": "NA",
                    "packetsSent": "3109",
                    "bytesSent": "3481886",
                    "senderId": "NA",
                    "remoteId": "2716e83d",
                    "nackCount": "0",
                    "framesEncoded": "387",
                    "framesSent": "NA",
                    "framesPerSecond": "NA"
                }
            },
            "remote-candidate": {
                "d8769f3f": {
                    "id": "d8769f3f",
                    "timestamp": "1624453857489",
                    "address": "192.168.1.12",
                    "port": "57374",
                    "protocol": "udp",
                    "candidateType": "prflx",
                    "url": "NA"
                },
                "1894b84e": {
                    "id": "1894b84e",
                    "timestamp": "1624453857489",
                    "address": "2a02:587:3e07:5100:e950:d005:6847:63d8",
                    "port": "57375",
                    "protocol": "udp",
                    "candidateType": "prflx",
                    "url": "NA"
                }
            }
        },
        {
            "candidate-pair": {
                "657fac51": {
                    "id": "657fac51",
                    "timestamp": "1624453859550",
                    "localCandidateId": "343fcaa5",
                    "remoteCandidateId": "1894b84e",
                    "state": "cancelled",
                    "priority": "7962083765675491000",
                    "nominated": "false",
                    "bytesSent": "0",
                    "currentRoundTripTime": "NA",
                    "totalRoundTripTime": "NA",
                    "bytesReceived": "0"
                },
                "70c07caf": {
                    "id": "70c07caf",
                    "timestamp": "1624453859550",
                    "localCandidateId": "97870ef5",
                    "remoteCandidateId": "d8769f3f",
                    "state": "succeeded",
                    "priority": "7961802290698650000",
                    "nominated": "true",
                    "bytesSent": "4274281",
                    "currentRoundTripTime": "NA",
                    "totalRoundTripTime": "NA",
                    "bytesReceived": "4233655"
                }
            },
            "inbound-rtp": {
                "5d967810": {
                    "id": "5d967810",
                    "timestamp": "1624453859551",
                    "ssrc": "1252115303",
                    "kind": "audio",
                    "transportId": "NA",
                    "codecId": "NA",
                    "packetsReceived": "827",
                    "packetsLost": "0",
                    "packetsDiscarded": "NA",
                    "jitter": "0.004",
                    "bytesReceived": "149847",
                    "receiverId": "NA",
                    "remoteId": "c75d25",
                    "nackCount": "0",
                    "audioLevel": "NA",
                    "framesDecoded": "NA",
                    "framesReceived": "NA",
                    "framesDropped": "NA",
                    "partialFramesLost": "NA",
                    "totalAudioEnergy": "NA",
                    "totalSamplesDuration": "NA"
                },
                "3b47280e": {
                    "id": "3b47280e",
                    "timestamp": "1624453859551",
                    "ssrc": "1159037486",
                    "kind": "video",
                    "transportId": "NA",
                    "codecId": "NA",
                    "packetsReceived": "3556",
                    "packetsLost": "0",
                    "packetsDiscarded": "NA",
                    "jitter": "0.011",
                    "bytesReceived": "3986836",
                    "receiverId": "NA",
                    "remoteId": "7e7749e2",
                    "nackCount": "0",
                    "audioLevel": "NA",
                    "framesDecoded": "452",
                    "framesReceived": "NA",
                    "framesDropped": "NA",
                    "partialFramesLost": "NA",
                    "totalAudioEnergy": "NA",
                    "totalSamplesDuration": "NA"
                }
            },
            "local-candidate": {
                "97870ef5": {
                    "id": "97870ef5",
                    "timestamp": "1624453859550",
                    "address": "192.168.1.12",
                    "port": "61357",
                    "protocol": "udp",
                    "candidateType": "host",
                    "url": "NA"
                },
                "f3e3d09c": {
                    "id": "f3e3d09c",
                    "timestamp": "1624453859550",
                    "address": "2.87.64.185",
                    "port": "61357",
                    "protocol": "udp",
                    "candidateType": "srflx",
                    "url": "NA"
                },
                "343fcaa5": {
                    "id": "343fcaa5",
                    "timestamp": "1624453859550",
                    "address": "2a02:587:3e07:5100:e950:d005:6847:63d8",
                    "port": "61358",
                    "protocol": "udp",
                    "candidateType": "host",
                    "url": "NA"
                },
                "62a26437": {
                    "id": "62a26437",
                    "timestamp": "1624453859550",
                    "address": "192.168.1.12",
                    "port": "65434",
                    "protocol": "tcp",
                    "candidateType": "host",
                    "url": "NA"
                },
                "7c433ea6": {
                    "id": "7c433ea6",
                    "timestamp": "1624453859550",
                    "address": "2a02:587:3e07:5100:e950:d005:6847:63d8",
                    "port": "52073",
                    "protocol": "tcp",
                    "candidateType": "host",
                    "url": "NA"
                }
            },
            "outbound-rtp": {
                "e1a31617": {
                    "id": "e1a31617",
                    "timestamp": "1624453859551",
                    "ssrc": "461880480",
                    "kind": "audio",
                    "transportId": "NA",
                    "codecId": "NA",
                    "packetsSent": "827",
                    "bytesSent": "149687",
                    "senderId": "NA",
                    "remoteId": "596474ca",
                    "nackCount": "0",
                    "framesEncoded": "NA",
                    "framesSent": "NA",
                    "framesPerSecond": "NA"
                },
                "27efc97d": {
                    "id": "27efc97d",
                    "timestamp": "1624453859551",
                    "ssrc": "2329479442",
                    "kind": "video",
                    "transportId": "NA",
                    "codecId": "NA",
                    "packetsSent": "3593",
                    "bytesSent": "4025959",
                    "senderId": "NA",
                    "remoteId": "2716e83d",
                    "nackCount": "0",
                    "framesEncoded": "446",
                    "framesSent": "NA",
                    "framesPerSecond": "NA"
                }
            },
            "remote-candidate": {
                "d8769f3f": {
                    "id": "d8769f3f",
                    "timestamp": "1624453859550",
                    "address": "192.168.1.12",
                    "port": "57374",
                    "protocol": "udp",
                    "candidateType": "prflx",
                    "url": "NA"
                },
                "1894b84e": {
                    "id": "1894b84e",
                    "timestamp": "1624453859550",
                    "address": "2a02:587:3e07:5100:e950:d005:6847:63d8",
                    "port": "57375",
                    "protocol": "udp",
                    "candidateType": "prflx",
                    "url": "NA"
                }
            }
        },
        {
            "candidate-pair": {
                "657fac51": {
                    "id": "657fac51",
                    "timestamp": "1624453861611",
                    "localCandidateId": "343fcaa5",
                    "remoteCandidateId": "1894b84e",
                    "state": "cancelled",
                    "priority": "7962083765675491000",
                    "nominated": "false",
                    "bytesSent": "0",
                    "currentRoundTripTime": "NA",
                    "totalRoundTripTime": "NA",
                    "bytesReceived": "0"
                },
                "70c07caf": {
                    "id": "70c07caf",
                    "timestamp": "1624453861611",
                    "localCandidateId": "97870ef5",
                    "remoteCandidateId": "d8769f3f",
                    "state": "succeeded",
                    "priority": "7961802290698650000",
                    "nominated": "true",
                    "bytesSent": "4841408",
                    "currentRoundTripTime": "NA",
                    "totalRoundTripTime": "NA",
                    "bytesReceived": "4843470"
                }
            },
            "inbound-rtp": {
                "5d967810": {
                    "id": "5d967810",
                    "timestamp": "1624453861611",
                    "ssrc": "1252115303",
                    "kind": "audio",
                    "transportId": "NA",
                    "codecId": "NA",
                    "packetsReceived": "930",
                    "packetsLost": "0",
                    "packetsDiscarded": "NA",
                    "jitter": "0.005",
                    "bytesReceived": "168490",
                    "receiverId": "NA",
                    "remoteId": "c75d25",
                    "nackCount": "0",
                    "audioLevel": "NA",
                    "framesDecoded": "NA",
                    "framesReceived": "NA",
                    "framesDropped": "NA",
                    "partialFramesLost": "NA",
                    "totalAudioEnergy": "NA",
                    "totalSamplesDuration": "NA"
                },
                "3b47280e": {
                    "id": "3b47280e",
                    "timestamp": "1624453861611",
                    "ssrc": "1159037486",
                    "kind": "video",
                    "transportId": "NA",
                    "codecId": "NA",
                    "packetsReceived": "4061",
                    "packetsLost": "0",
                    "packetsDiscarded": "NA",
                    "jitter": "0.012",
                    "bytesReceived": "4564748",
                    "receiverId": "NA",
                    "remoteId": "7e7749e2",
                    "nackCount": "0",
                    "audioLevel": "NA",
                    "framesDecoded": "507",
                    "framesReceived": "NA",
                    "framesDropped": "NA",
                    "partialFramesLost": "NA",
                    "totalAudioEnergy": "NA",
                    "totalSamplesDuration": "NA"
                }
            },
            "local-candidate": {
                "97870ef5": {
                    "id": "97870ef5",
                    "timestamp": "1624453861611",
                    "address": "192.168.1.12",
                    "port": "61357",
                    "protocol": "udp",
                    "candidateType": "host",
                    "url": "NA"
                },
                "f3e3d09c": {
                    "id": "f3e3d09c",
                    "timestamp": "1624453861611",
                    "address": "2.87.64.185",
                    "port": "61357",
                    "protocol": "udp",
                    "candidateType": "srflx",
                    "url": "NA"
                },
                "343fcaa5": {
                    "id": "343fcaa5",
                    "timestamp": "1624453861611",
                    "address": "2a02:587:3e07:5100:e950:d005:6847:63d8",
                    "port": "61358",
                    "protocol": "udp",
                    "candidateType": "host",
                    "url": "NA"
                },
                "62a26437": {
                    "id": "62a26437",
                    "timestamp": "1624453861611",
                    "address": "192.168.1.12",
                    "port": "65434",
                    "protocol": "tcp",
                    "candidateType": "host",
                    "url": "NA"
                },
                "7c433ea6": {
                    "id": "7c433ea6",
                    "timestamp": "1624453861611",
                    "address": "2a02:587:3e07:5100:e950:d005:6847:63d8",
                    "port": "52073",
                    "protocol": "tcp",
                    "candidateType": "host",
                    "url": "NA"
                }
            },
            "outbound-rtp": {
                "e1a31617": {
                    "id": "e1a31617",
                    "timestamp": "1624453861611",
                    "ssrc": "461880480",
                    "kind": "audio",
                    "transportId": "NA",
                    "codecId": "NA",
                    "packetsSent": "931",
                    "bytesSent": "168511",
                    "senderId": "NA",
                    "remoteId": "596474ca",
                    "nackCount": "0",
                    "framesEncoded": "NA",
                    "framesSent": "NA",
                    "framesPerSecond": "NA"
                },
                "27efc97d": {
                    "id": "27efc97d",
                    "timestamp": "1624453861611",
                    "ssrc": "2329479442",
                    "kind": "video",
                    "transportId": "NA",
                    "codecId": "NA",
                    "packetsSent": "4065",
                    "bytesSent": "4561642",
                    "senderId": "NA",
                    "remoteId": "2716e83d",
                    "nackCount": "0",
                    "framesEncoded": "499",
                    "framesSent": "NA",
                    "framesPerSecond": "NA"
                }
            },
            "remote-candidate": {
                "d8769f3f": {
                    "id": "d8769f3f",
                    "timestamp": "1624453861611",
                    "address": "192.168.1.12",
                    "port": "57374",
                    "protocol": "udp",
                    "candidateType": "prflx",
                    "url": "NA"
                },
                "1894b84e": {
                    "id": "1894b84e",
                    "timestamp": "1624453861611",
                    "address": "2a02:587:3e07:5100:e950:d005:6847:63d8",
                    "port": "57375",
                    "protocol": "udp",
                    "candidateType": "prflx",
                    "url": "NA"
                }
            }
        },
        {
            "candidate-pair": {
                "657fac51": {
                    "id": "657fac51",
                    "timestamp": "1624453863668",
                    "localCandidateId": "343fcaa5",
                    "remoteCandidateId": "1894b84e",
                    "state": "cancelled",
                    "priority": "7962083765675491000",
                    "nominated": "false",
                    "bytesSent": "0",
                    "currentRoundTripTime": "NA",
                    "totalRoundTripTime": "NA",
                    "bytesReceived": "0"
                },
                "70c07caf": {
                    "id": "70c07caf",
                    "timestamp": "1624453863668",
                    "localCandidateId": "97870ef5",
                    "remoteCandidateId": "d8769f3f",
                    "state": "succeeded",
                    "priority": "7961802290698650000",
                    "nominated": "true",
                    "bytesSent": "5237769",
                    "currentRoundTripTime": "NA",
                    "totalRoundTripTime": "NA",
                    "bytesReceived": "5221236"
                }
            },
            "inbound-rtp": {
                "5d967810": {
                    "id": "5d967810",
                    "timestamp": "1624453863668",
                    "ssrc": "1252115303",
                    "kind": "audio",
                    "transportId": "NA",
                    "codecId": "NA",
                    "packetsReceived": "1033",
                    "packetsLost": "0",
                    "packetsDiscarded": "NA",
                    "jitter": "0.005",
                    "bytesReceived": "186973",
                    "receiverId": "NA",
                    "remoteId": "c75d25",
                    "nackCount": "0",
                    "audioLevel": "NA",
                    "framesDecoded": "NA",
                    "framesReceived": "NA",
                    "framesDropped": "NA",
                    "partialFramesLost": "NA",
                    "totalAudioEnergy": "NA",
                    "totalSamplesDuration": "NA"
                },
                "3b47280e": {
                    "id": "3b47280e",
                    "timestamp": "1624453863669",
                    "ssrc": "1159037486",
                    "kind": "video",
                    "transportId": "NA",
                    "codecId": "NA",
                    "packetsReceived": "4382",
                    "packetsLost": "0",
                    "packetsDiscarded": "NA",
                    "jitter": "0.004",
                    "bytesReceived": "4914359",
                    "receiverId": "NA",
                    "remoteId": "7e7749e2",
                    "nackCount": "0",
                    "audioLevel": "NA",
                    "framesDecoded": "563",
                    "framesReceived": "NA",
                    "framesDropped": "NA",
                    "partialFramesLost": "NA",
                    "totalAudioEnergy": "NA",
                    "totalSamplesDuration": "NA"
                }
            },
            "local-candidate": {
                "97870ef5": {
                    "id": "97870ef5",
                    "timestamp": "1624453863668",
                    "address": "192.168.1.12",
                    "port": "61357",
                    "protocol": "udp",
                    "candidateType": "host",
                    "url": "NA"
                },
                "f3e3d09c": {
                    "id": "f3e3d09c",
                    "timestamp": "1624453863668",
                    "address": "2.87.64.185",
                    "port": "61357",
                    "protocol": "udp",
                    "candidateType": "srflx",
                    "url": "NA"
                },
                "343fcaa5": {
                    "id": "343fcaa5",
                    "timestamp": "1624453863668",
                    "address": "2a02:587:3e07:5100:e950:d005:6847:63d8",
                    "port": "61358",
                    "protocol": "udp",
                    "candidateType": "host",
                    "url": "NA"
                },
                "62a26437": {
                    "id": "62a26437",
                    "timestamp": "1624453863668",
                    "address": "192.168.1.12",
                    "port": "65434",
                    "protocol": "tcp",
                    "candidateType": "host",
                    "url": "NA"
                },
                "7c433ea6": {
                    "id": "7c433ea6",
                    "timestamp": "1624453863668",
                    "address": "2a02:587:3e07:5100:e950:d005:6847:63d8",
                    "port": "52073",
                    "protocol": "tcp",
                    "candidateType": "host",
                    "url": "NA"
                }
            },
            "outbound-rtp": {
                "e1a31617": {
                    "id": "e1a31617",
                    "timestamp": "1624453863668",
                    "ssrc": "461880480",
                    "kind": "audio",
                    "transportId": "NA",
                    "codecId": "NA",
                    "packetsSent": "1033",
                    "bytesSent": "187133",
                    "senderId": "NA",
                    "remoteId": "596474ca",
                    "nackCount": "0",
                    "framesEncoded": "NA",
                    "framesSent": "NA",
                    "framesPerSecond": "NA"
                },
                "27efc97d": {
                    "id": "27efc97d",
                    "timestamp": "1624453863668",
                    "ssrc": "2329479442",
                    "kind": "video",
                    "transportId": "NA",
                    "codecId": "NA",
                    "packetsSent": "4405",
                    "bytesSent": "4929433",
                    "senderId": "NA",
                    "remoteId": "2716e83d",
                    "nackCount": "0",
                    "framesEncoded": "556",
                    "framesSent": "NA",
                    "framesPerSecond": "NA"
                }
            },
            "remote-candidate": {
                "d8769f3f": {
                    "id": "d8769f3f",
                    "timestamp": "1624453863668",
                    "address": "192.168.1.12",
                    "port": "57374",
                    "protocol": "udp",
                    "candidateType": "prflx",
                    "url": "NA"
                },
                "1894b84e": {
                    "id": "1894b84e",
                    "timestamp": "1624453863668",
                    "address": "2a02:587:3e07:5100:e950:d005:6847:63d8",
                    "port": "57375",
                    "protocol": "udp",
                    "candidateType": "prflx",
                    "url": "NA"
                }
            }
        },
        {
            "candidate-pair": {
                "657fac51": {
                    "id": "657fac51",
                    "timestamp": "1624453865724",
                    "localCandidateId": "343fcaa5",
                    "remoteCandidateId": "1894b84e",
                    "state": "cancelled",
                    "priority": "7962083765675491000",
                    "nominated": "false",
                    "bytesSent": "0",
                    "currentRoundTripTime": "NA",
                    "totalRoundTripTime": "NA",
                    "bytesReceived": "0"
                },
                "70c07caf": {
                    "id": "70c07caf",
                    "timestamp": "1624453865724",
                    "localCandidateId": "97870ef5",
                    "remoteCandidateId": "d8769f3f",
                    "state": "succeeded",
                    "priority": "7961802290698650000",
                    "nominated": "true",
                    "bytesSent": "5841446",
                    "currentRoundTripTime": "NA",
                    "totalRoundTripTime": "NA",
                    "bytesReceived": "5824099"
                }
            },
            "inbound-rtp": {
                "5d967810": {
                    "id": "5d967810",
                    "timestamp": "1624453865724",
                    "ssrc": "1252115303",
                    "kind": "audio",
                    "transportId": "NA",
                    "codecId": "NA",
                    "packetsReceived": "1136",
                    "packetsLost": "0",
                    "packetsDiscarded": "NA",
                    "jitter": "0.004",
                    "bytesReceived": "205616",
                    "receiverId": "NA",
                    "remoteId": "c75d25",
                    "nackCount": "0",
                    "audioLevel": "NA",
                    "framesDecoded": "NA",
                    "framesReceived": "NA",
                    "framesDropped": "NA",
                    "partialFramesLost": "NA",
                    "totalAudioEnergy": "NA",
                    "totalSamplesDuration": "NA"
                },
                "3b47280e": {
                    "id": "3b47280e",
                    "timestamp": "1624453865724",
                    "ssrc": "1159037486",
                    "kind": "video",
                    "transportId": "NA",
                    "codecId": "NA",
                    "packetsReceived": "4888",
                    "packetsLost": "0",
                    "packetsDiscarded": "NA",
                    "jitter": "0.015",
                    "bytesReceived": "5485275",
                    "receiverId": "NA",
                    "remoteId": "7e7749e2",
                    "nackCount": "0",
                    "audioLevel": "NA",
                    "framesDecoded": "616",
                    "framesReceived": "NA",
                    "framesDropped": "NA",
                    "partialFramesLost": "NA",
                    "totalAudioEnergy": "NA",
                    "totalSamplesDuration": "NA"
                }
            },
            "local-candidate": {
                "97870ef5": {
                    "id": "97870ef5",
                    "timestamp": "1624453865724",
                    "address": "192.168.1.12",
                    "port": "61357",
                    "protocol": "udp",
                    "candidateType": "host",
                    "url": "NA"
                },
                "f3e3d09c": {
                    "id": "f3e3d09c",
                    "timestamp": "1624453865724",
                    "address": "2.87.64.185",
                    "port": "61357",
                    "protocol": "udp",
                    "candidateType": "srflx",
                    "url": "NA"
                },
                "343fcaa5": {
                    "id": "343fcaa5",
                    "timestamp": "1624453865724",
                    "address": "2a02:587:3e07:5100:e950:d005:6847:63d8",
                    "port": "61358",
                    "protocol": "udp",
                    "candidateType": "host",
                    "url": "NA"
                },
                "62a26437": {
                    "id": "62a26437",
                    "timestamp": "1624453865724",
                    "address": "192.168.1.12",
                    "port": "65434",
                    "protocol": "tcp",
                    "candidateType": "host",
                    "url": "NA"
                },
                "7c433ea6": {
                    "id": "7c433ea6",
                    "timestamp": "1624453865724",
                    "address": "2a02:587:3e07:5100:e950:d005:6847:63d8",
                    "port": "52073",
                    "protocol": "tcp",
                    "candidateType": "host",
                    "url": "NA"
                }
            },
            "outbound-rtp": {
                "e1a31617": {
                    "id": "e1a31617",
                    "timestamp": "1624453865724",
                    "ssrc": "461880480",
                    "kind": "audio",
                    "transportId": "NA",
                    "codecId": "NA",
                    "packetsSent": "1136",
                    "bytesSent": "205776",
                    "senderId": "NA",
                    "remoteId": "596474ca",
                    "nackCount": "0",
                    "framesEncoded": "NA",
                    "framesSent": "NA",
                    "framesPerSecond": "NA"
                },
                "27efc97d": {
                    "id": "27efc97d",
                    "timestamp": "1624453865724",
                    "ssrc": "2329479442",
                    "kind": "video",
                    "transportId": "NA",
                    "codecId": "NA",
                    "packetsSent": "4914",
                    "bytesSent": "5501351",
                    "senderId": "NA",
                    "remoteId": "2716e83d",
                    "nackCount": "0",
                    "framesEncoded": "612",
                    "framesSent": "NA",
                    "framesPerSecond": "NA"
                }
            },
            "remote-candidate": {
                "d8769f3f": {
                    "id": "d8769f3f",
                    "timestamp": "1624453865724",
                    "address": "192.168.1.12",
                    "port": "57374",
                    "protocol": "udp",
                    "candidateType": "prflx",
                    "url": "NA"
                },
                "1894b84e": {
                    "id": "1894b84e",
                    "timestamp": "1624453865724",
                    "address": "2a02:587:3e07:5100:e950:d005:6847:63d8",
                    "port": "57375",
                    "protocol": "udp",
                    "candidateType": "prflx",
                    "url": "NA"
                }
            }
        }
    ],
    "Network Profile": "",
    "Region Id": "NC",
    "Itinerary": "0"
}